Workbook

Sheet INSTRUCTIONS
A1: Cash Flow Planner (Basic)
A3: Purpose
A4: Plan your cash position over the next 90 days using simple averages.
A5: This helps you spot cash gaps early and test simple scenarios.
A7: How to use (simple)
A8: 1) Fill in the yellow cells in SETUP.
A9: 2) (Optional) Add any one-off payments or one-off income in ONE_OFF_EVENTS.
A10: 3) Review WEEKLY_PLANNER for an overview and DAILY_PLANNER for detail.
A11: 4) Use the scenario % changes in SETUP to test 'what if' situations.
A13: Notes
A14: • Enter figures ex VAT.
A15: • This is a planning tool. If your inputs change, update SETUP and it will refresh.

Sheet SETUP
A1: SETUP (fill yellow cells)
A3: Opening cash (bank + till) | B3: 10000 | C3: Tip | D3: Your starting cash today.
A4: Forecast start date | B4: 2026-01-22 | C4: Tip | D4: Leave as today, or change to the day you want to start.
A5: Average daily sales (ex VAT) | B5: 1500 | C5: Tip | D5: Last 7 days total ÷ 7 (or last 30 days ÷ 30).
A6: Average gross margin % | B6: 0.23 | C6: Tip | D6: If unsure, start with 40%.
A7: Card fees % (average) | B7: 0.35 | C7: Tip | D7: If unsure, use 1.5–2.0%.
A8: Monthly rent | B8: 4000 | C8: Tip | D8: Rent only.
A9: Monthly wages | B9: 6000 | C9: Tip | D9: Total wages incl. NI.
A10: Other monthly fixed costs | B10: 1500 | C10: Tip | D10: Utilities, insurance, software, etc.
A11: Days open per week | B11: 7 | C11: Tip | D11: Most businesses are 5–7.
A12: Assumptions
A13: Weeks per month | B13: 4.3452 | D13: Used to convert monthly costs to weekly.
A14: Days per month | B14: 30.4375 | D14: Used to convert monthly costs to daily.
A16: SCENARIOS (optional)
A17: Sales change % | B17: 0 | C17: Tip | D17: Example: -10% for a sales drop.
A18: Margin change (percentage points) | B18: 0 | C18: Tip | D18: Example: -5% means 45% becomes 40%.
A19: Rent change % | B19: 0 | C19: Tip
A20: Wages change % | B20: 0 | C20: Tip
A21: Other costs change % | B21: 0 | C21: Tip
A22: Card fees change (percentage points) | B22: 0 | C22: Tip | D22: Example: +0.2% means 1.8% becomes 2.0%.

Sheet ONE_OFF_EVENTS
A1: ONE-OFF EVENTS (optional)
A2: Add one-off income or one-off payments here. Amounts: positive = money in, negative = money out.
A4: Date | B4: Description | C4: Amount (ex VAT) | D4: Notes

Sheet WEEKLY_PLANNER
A3: Week # | B3: Week Start | C3: Sales (week) | D3: Gross Profit | E3: Card Fees | F3: Fixed Costs (week) | G3: One-off events | H3: Net Cash Change | I3: Opening Cash | J3: Closing Cash
A4: 1 | B4: =SETUP!$B$4+0*7 -> 46044 | C4: =SUM(DAILY_PLANNER!C4:C10) -> 10500 | D4: =SUM(DAILY_PLANNER!D4:D10) -> 2415 | E4: =SUM(DAILY_PLANNER!E4:E10) -> 3675 | F4: =SUM(DAILY_PLANNER!F4:F10) -> 2644.7639 | G4: =SUM(DAILY_PLANNER!G4:G10) -> 0 | H4: =SUM(DAILY_PLANNER!H4:H10) -> -3904.7639 | I4: =SETUP!$B$3 -> 10000 | J4: =I4+H4 -> 6095.2361
A5: 2 | B5: =SETUP!$B$4+1*7 -> 46051 | C5: =SUM(DAILY_PLANNER!C11:C17) -> 10500 | D5: =SUM(DAILY_PLANNER!D11:D17) -> 2415 | E5: =SUM(DAILY_PLANNER!E11:E17) -> 3675 | F5: =SUM(DAILY_PLANNER!F11:F17) -> 2644.7639 | G5: =SUM(DAILY_PLANNER!G11:G17) -> 0 | H5: =SUM(DAILY_PLANNER!H11:H17) -> -3904.7639 | I5: =J4 -> 6095.2361 | J5: =I5+H5 -> 2190.4723
A6: 3 | B6: =SETUP!$B$4+2*7 -> 46058 | C6: =SUM(DAILY_PLANNER!C18:C24) -> 10500 | D6: =SUM(DAILY_PLANNER!D18:D24) -> 2415 | E6: =SUM(DAILY_PLANNER!E18:E24) -> 3675 | F6: =SUM(DAILY_PLANNER!F18:F24) -> 2644.7639 | G6: =SUM(DAILY_PLANNER!G18:G24) -> 0 | H6: =SUM(DAILY_PLANNER!H18:H24) -> -3904.7639 | I6: =J5 -> 2190.4723 | J6: =I6+H6 -> -1714.2916
A7: 4 | B7: =SETUP!$B$4+3*7 -> 46065 | C7: =SUM(DAILY_PLANNER!C25:C31) -> 10500 | D7: =SUM(DAILY_PLANNER!D25:D31) -> 2415 | E7: =SUM(DAILY_PLANNER!E25:E31) -> 3675 | F7: =SUM(DAILY_PLANNER!F25:F31) -> 2644.7639 | G7: =SUM(DAILY_PLANNER!G25:G31) -> 0 | H7: =SUM(DAILY_PLANNER!H25:H31) -> -3904.7639 | I7: =J6 -> -1714.2916 | J7: =I7+H7 -> -5619.0554
A8: 5 | B8: =SETUP!$B$4+4*7 -> 46072 | C8: =SUM(DAILY_PLANNER!C32:C38) -> 10500 | D8: =SUM(DAILY_PLANNER!D32:D38) -> 2415 | E8: =SUM(DAILY_PLANNER!E32:E38) -> 3675 | F8: =SUM(DAILY_PLANNER!F32:F38) -> 2644.7639 | G8: =SUM(DAILY_PLANNER!G32:G38) -> 0 | H8: =SUM(DAILY_PLANNER!H32:H38) -> -3904.7639 | I8: =J7 -> -5619.0554 | J8: =I8+H8 -> -9523.8193
A9: 6 | B9: =SETUP!$B$4+5*7 -> 46079 | C9: =SUM(DAILY_PLANNER!C39:C45) -> 10500 | D9: =SUM(DAILY_PLANNER!D39:D45) -> 2415 | E9: =SUM(DAILY_PLANNER!E39:E45) -> 3675 | F9: =SUM(DAILY_PLANNER!F39:F45) -> 2644.7639 | G9: =SUM(DAILY_PLANNER!G39:G45) -> 0 | H9: =SUM(DAILY_PLANNER!H39:H45) -> -3904.7639 | I9: =J8 -> -9523.8193 | J9: =I9+H9 -> -13428.583
A10: 7 | B10: =SETUP!$B$4+6*7 -> 46086 | C10: =SUM(DAILY_PLANNER!C46:C52) -> 10500 | D10: =SUM(DAILY_PLANNER!D46:D52) -> 2415 | E10: =SUM(DAILY_PLANNER!E46:E52) -> 3675 | F10: =SUM(DAILY_PLANNER!F46:F52) -> 2644.7639 | G10: =SUM(DAILY_PLANNER!G46:G52) -> 0 | H10: =SUM(DAILY_PLANNER!H46:H52) -> -3904.7639 | I10: =J9 -> -13428.583 | J10: =I10+H10 -> -17333.347
A11: 8 | B11: =SETUP!$B$4+7*7 -> 46093 | C11: =SUM(DAILY_PLANNER!C53:C59) -> 10500 | D11: =SUM(DAILY_PLANNER!D53:D59) -> 2415 | E11: =SUM(DAILY_PLANNER!E53:E59) -> 3675 | F11: =SUM(DAILY_PLANNER!F53:F59) -> 2644.7639 | G11: =SUM(DAILY_PLANNER!G53:G59) -> 0 | H11: =SUM(DAILY_PLANNER!H53:H59) -> -3904.7639 | I11: =J10 -> -17333.347 | J11: =I11+H11 -> -21238.111
A12: 9 | B12: =SETUP!$B$4+8*7 -> 46100 | C12: =SUM(DAILY_PLANNER!C60:C66) -> 10500 | D12: =SUM(DAILY_PLANNER!D60:D66) -> 2415 | E12: =SUM(DAILY_PLANNER!E60:E66) -> 3675 | F12: =SUM(DAILY_PLANNER!F60:F66) -> 2644.7639 | G12: =SUM(DAILY_PLANNER!G60:G66) -> 0 | H12: =SUM(DAILY_PLANNER!H60:H66) -> -3904.7639 | I12: =J11 -> -21238.111 | J12: =I12+H12 -> -25142.875
A13: 10 | B13: =SETUP!$B$4+9*7 -> 46107 | C13: =SUM(DAILY_PLANNER!C67:C73) -> 10500 | D13: =SUM(DAILY_PLANNER!D67:D73) -> 2415 | E13: =SUM(DAILY_PLANNER!E67:E73) -> 3675 | F13: =SUM(DAILY_PLANNER!F67:F73) -> 2644.7639 | G13: =SUM(DAILY_PLANNER!G67:G73) -> 0 | H13: =SUM(DAILY_PLANNER!H67:H73) -> -3904.7639 | I13: =J12 -> -25142.875 | J13: =I13+H13 -> -29047.639
A14: 11 | B14: =SETUP!$B$4+10*7 -> 46114 | C14: =SUM(DAILY_PLANNER!C74:C80) -> 10500 | D14: =SUM(DAILY_PLANNER!D74:D80) -> 2415 | E14: =SUM(DAILY_PLANNER!E74:E80) -> 3675 | F14: =SUM(DAILY_PLANNER!F74:F80) -> 2644.7639 | G14: =SUM(DAILY_PLANNER!G74:G80) -> 0 | H14: =SUM(DAILY_PLANNER!H74:H80) -> -3904.7639 | I14: =J13 -> -29047.639 | J14: =I14+H14 -> -32952.402
A15: 12 | B15: =SETUP!$B$4+11*7 -> 46121 | C15: =SUM(DAILY_PLANNER!C81:C87) -> 10500 | D15: =SUM(DAILY_PLANNER!D81:D87) -> 2415 | E15: =SUM(DAILY_PLANNER!E81:E87) -> 3675 | F15: =SUM(DAILY_PLANNER!F81:F87) -> 2644.7639 | G15: =SUM(DAILY_PLANNER!G81:G87) -> 0 | H15: =SUM(DAILY_PLANNER!H81:H87) -> -3904.7639 | I15: =J14 -> -32952.402 | J15: =I15+H15 -> -36857.166
A16: 13 | B16: =SETUP!$B$4+12*7 -> 46128 | C16: =SUM(DAILY_PLANNER!C88:C94) -> 9000 | D16: =SUM(DAILY_PLANNER!D88:D94) -> 2070 | E16: =SUM(DAILY_PLANNER!E88:E94) -> 3150 | F16: =SUM(DAILY_PLANNER!F88:F94) -> 2266.9405 | G16: =SUM(DAILY_PLANNER!G88:G94) -> 0 | H16: =SUM(DAILY_PLANNER!H88:H94) -> -3346.9405 | I16: =J15 -> -36857.166 | J16: =I16+H16 -> -40204.107

Sheet DAILY_PLANNER
A3: Date | B3: Day | C3: Sales (ex VAT) | D3: Gross Profit | E3: Card Fees | F3: Fixed Costs (daily) | G3: One-off events | H3: Net Cash Change | I3: Opening Cash | J3: Closing Cash
A4: =SETUP!$B$4+0 -> 46044 | B4: =TEXT(A4,"ddd") -> Thu | C4: =SETUP!$B$5*(1+SETUP!$B$17) -> 1500 | D4: =C4*(SETUP!$B$6+SETUP!$B$18) -> 345 | E4: =C4*(SETUP!$B$7+SETUP!$B$22) -> 525 | F4: =((SETUP!$B$8*(1+SETUP!$B$19)+SETUP!$B$9*(1+SETUP!$B$20)+SETUP!$B$10*(1+SETUP!$B$21))/SETUP!$B$14) -> 377.82341 | G4: =SUMIF(ONE_OFF_EVENTS!$A$5:$A$104,A4,ONE_OFF_EVENTS!$C$5:$C$104) -> 0 | H4: =D4-E4-F4+G4 -> -557.82341 | I4: =SETUP!$B$3 -> 10000 | J4: =I4+H4 -> 9442.1766
A5: =SETUP!$B$4+1 -> 46045 | B5: =TEXT(A5,"ddd") -> Fri | C5: =SETUP!$B$5*(1+SETUP!$B$17) -> 1500 | D5: =C5*(SETUP!$B$6+SETUP!$B$18) -> 345 | E5: =C5*(SETUP!$B$7+SETUP!$B$22) -> 525 | F5: =((SETUP!$B$8*(1+SETUP!$B$19)+SETUP!$B$9*(1+SETUP!$B$20)+SETUP!$B$10*(1+SETUP!$B$21))/SETUP!$B$14) -> 377.82341 | G5: =SUMIF(ONE_OFF_EVENTS!$A$5:$A$104,A5,ONE_OFF_EVENTS!$C$5:$C$104) -> 0 | H5: =D5-E5-F5+G5 -> -557.82341 | I5: =J4 -> 9442.1766 | J5: =I5+H5 -> 8884.3532
A6: =SETUP!$B$4+2 -> 46046 | B6: =TEXT(A6,"ddd") -> Sat | C6: =SETUP!$B$5*(1+SETUP!$B$17) -> 1500 | D6: =C6*(SETUP!$B$6+SETUP!$B$18) -> 345 | E6: =C6*(SETUP!$B$7+SETUP!$B$22) -> 525 | F6: =((SETUP!$B$8*(1+SETUP!$B$19)+SETUP!$B$9*(1+SETUP!$B$20)+SETUP!$B$10*(1+SETUP!$B$21))/SETUP!$B$14) -> 377.82341 | G6: =SUMIF(ONE_OFF_EVENTS!$A$5:$A$104,A6,ONE_OFF_EVENTS!$C$5:$C$104) -> 0 | H6: =D6-E6-F6+G6 -> -557.82341 | I6: =J5 -> 8884.3532 | J6: =I6+H6 -> 8326.5298
A7: =SETUP!$B$4+3 -> 46047 | B7: =TEXT(A7,"ddd") -> Sun | C7: =SETUP!$B$5*(1+SETUP!$B$17) -> 1500 | D7: =C7*(SETUP!$B$6+SETUP!$B$18) -> 345 | E7: =C7*(SETUP!$B$7+SETUP!$B$22) -> 525 | F7: =((SETUP!$B$8*(1+SETUP!$B$19)+SETUP!$B$9*(1+SETUP!$B$20)+SETUP!$B$10*(1+SETUP!$B$21))/SETUP!$B$14) -> 377.82341 | G7: =SUMIF(ONE_OFF_EVENTS!$A$5:$A$104,A7,ONE_OFF_EVENTS!$C$5:$C$104) -> 0 | H7: =D7-E7-F7+G7 -> -557.82341 | I7: =J6 -> 8326.5298 | J7: =I7+H7 -> 7768.7064
A8: =SETUP!$B$4+4 -> 46048 | B8: =TEXT(A8,"ddd") -> Mon | C8: =SETUP!$B$5*(1+SETUP!$B$17) -> 1500 | D8: =C8*(SETUP!$B$6+SETUP!$B$18) -> 345 | E8: =C8*(SETUP!$B$7+SETUP!$B$22) -> 525 | F8: =((SETUP!$B$8*(1+SETUP!$B$19)+SETUP!$B$9*(1+SETUP!$B$20)+SETUP!$B$10*(1+SETUP!$B$21))/SETUP!$B$14) -> 377.82341 | G8: =SUMIF(ONE_OFF_EVENTS!$A$5:$A$104,A8,ONE_OFF_EVENTS!$C$5:$C$104) -> 0 | H8: =D8-E8-F8+G8 -> -557.82341 | I8: =J7 -> 7768.7064 | J8: =I8+H8 -> 7210.883
A9: =SETUP!$B$4+5 -> 46049 | B9: =TEXT(A9,"ddd") -> Tue | C9: =SETUP!$B$5*(1+SETUP!$B$17) -> 1500 | D9: =C9*(SETUP!$B$6+SETUP!$B$18) -> 345 | E9: =C9*(SETUP!$B$7+SETUP!$B$22) -> 525 | F9: =((SETUP!$B$8*(1+SETUP!$B$19)+SETUP!$B$9*(1+SETUP!$B$20)+SETUP!$B$10*(1+SETUP!$B$21))/SETUP!$B$14) -> 377.82341 | G9: =SUMIF(ONE_OFF_EVENTS!$A$5:$A$104,A9,ONE_OFF_EVENTS!$C$5:$C$104) -> 0 | H9: =D9-E9-F9+G9 -> -557.82341 | I9: =J8 -> 7210.883 | J9: =I9+H9 -> 6653.0595
A10: =SETUP!$B$4+6 -> 46050 | B10: =TEXT(A10,"ddd") -> Wed | C10: =SETUP!$B$5*(1+SETUP!$B$17) -> 1500 | D10: =C10*(SETUP!$B$6+SETUP!$B$18) -> 345 | E10: =C10*(SETUP!$B$7+SETUP!$B$22) -> 525 | F10: =((SETUP!$B$8*(1+SETUP!$B$19)+SETUP!$B$9*(1+SETUP!$B$20)+SETUP!$B$10*(1+SETUP!$B$21))/SETUP!$B$14) -> 377.82341 | G10: =SUMIF(ONE_OFF_EVENTS!$A$5:$A$104,A10,ONE_OFF_EVENTS!$C$5:$C$104) -> 0 | H10: =D10-E10-F10+G10 -> -557.82341 | I10: =J9 -> 6653.0595 | J10: =I10+H10 -> 6095.2361
A11: =SETUP!$B$4+7 -> 46051 | B11: =TEXT(A11,"ddd") -> Thu | C11: =SETUP!$B$5*(1+SETUP!$B$17) -> 1500 | D11: =C11*(SETUP!$B$6+SETUP!$B$18) -> 345 | E11: =C11*(SETUP!$B$7+SETUP!$B$22) -> 525 | F11: =((SETUP!$B$8*(1+SETUP!$B$19)+SETUP!$B$9*(1+SETUP!$B$20)+SETUP!$B$10*(1+SETUP!$B$21))/SETUP!$B$14) -> 377.82341 | G11: =SUMIF(ONE_OFF_EVENTS!$A$5:$A$104,A11,ONE_OFF_EVENTS!$C$5:$C$104) -> 0 | H11: =D11-E11-F11+G11 -> -557.82341 | I11: =J10 -> 6095.2361 | J11: =I11+H11 -> 5537.4127
A12: =SETUP!$B$4+8 -> 46052 | B12: =TEXT(A12,"ddd") -> Fri | C12: =SETUP!$B$5*(1+SETUP!$B$17) -> 1500 | D12: =C12*(SETUP!$B$6+SETUP!$B$18) -> 345 | E12: =C12*(SETUP!$B$7+SETUP!$B$22) -> 525 | F12: =((SETUP!$B$8*(1+SETUP!$B$19)+SETUP!$B$9*(1+SETUP!$B$20)+SETUP!$B$10*(1+SETUP!$B$21))/SETUP!$B$14) -> 377.82341 | G12: =SUMIF(ONE_OFF_EVENTS!$A$5:$A$104,A12,ONE_OFF_EVENTS!$C$5:$C$104) -> 0 | H12: =D12-E12-F12+G12 -> -557.82341 | I12: =J11 -> 5537.4127 | J12: =I12+H12 -> 4979.5893
A13: =SETUP!$B$4+9 -> 46053 | B13: =TEXT(A13,"ddd") -> Sat | C13: =SETUP!$B$5*(1+SETUP!$B$17) -> 1500 | D13: =C13*(SETUP!$B$6+SETUP!$B$18) -> 345 | E13: =C13*(SETUP!$B$7+SETUP!$B$22) -> 525 | F13: =((SETUP!$B$8*(1+SETUP!$B$19)+SETUP!$B$9*(1+SETUP!$B$20)+SETUP!$B$10*(1+SETUP!$B$21))/SETUP!$B$14) -> 377.82341 | G13: =SUMIF(ONE_OFF_EVENTS!$A$5:$A$104,A13,ONE_OFF_EVENTS!$C$5:$C$104) -> 0 | H13: =D13-E13-F13+G13 -> -557.82341 | I13: =J12 -> 4979.5893 | J13: =I13+H13 -> 4421.7659
A14: =SETUP!$B$4+10 -> 46054 | B14: =TEXT(A14,"ddd") -> Sun | C14: =SETUP!$B$5*(1+SETUP!$B$17) -> 1500 | D14: =C14*(SETUP!$B$6+SETUP!$B$18) -> 345 | E14: =C14*(SETUP!$B$7+SETUP!$B$22) -> 525 | F14: =((SETUP!$B$8*(1+SETUP!$B$19)+SETUP!$B$9*(1+SETUP!$B$20)+SETUP!$B$10*(1+SETUP!$B$21))/SETUP!$B$14) -> 377.82341 | G14: =SUMIF(ONE_OFF_EVENTS!$A$5:$A$104,A14,ONE_OFF_EVENTS!$C$5:$C$104) -> 0 | H14: =D14-E14-F14+G14 -> -557.82341 | I14: =J13 -> 4421.7659 | J14: =I14+H14 -> 3863.9425
A15: =SETUP!$B$4+11 -> 46055 | B15: =TEXT(A15,"ddd") -> Mon | C15: =SETUP!$B$5*(1+SETUP!$B$17) -> 1500 | D15: =C15*(SETUP!$B$6+SETUP!$B$18) -> 345 | E15: =C15*(SETUP!$B$7+SETUP!$B$22) -> 525 | F15: =((SETUP!$B$8*(1+SETUP!$B$19)+SETUP!$B$9*(1+SETUP!$B$20)+SETUP!$B$10*(1+SETUP!$B$21))/SETUP!$B$14) -> 377.82341 | G15: =SUMIF(ONE_OFF_EVENTS!$A$5:$A$104,A15,ONE_OFF_EVENTS!$C$5:$C$104) -> 0 | H15: =D15-E15-F15+G15 -> -557.82341 | I15: =J14 -> 3863.9425 | J15: =I15+H15 -> 3306.1191
A16: =SETUP!$B$4+12 -> 46056 | B16: =TEXT(A16,"ddd") -> Tue | C16: =SETUP!$B$5*(1+SETUP!$B$17) -> 1500 | D16: =C16*(SETUP!$B$6+SETUP!$B$18) -> 345 | E16: =C16*(SETUP!$B$7+SETUP!$B$22) -> 525 | F16: =((SETUP!$B$8*(1+SETUP!$B$19)+SETUP!$B$9*(1+SETUP!$B$20)+SETUP!$B$10*(1+SETUP!$B$21))/SETUP!$B$14) -> 377.82341 | G16: =SUMIF(ONE_OFF_EVENTS!$A$5:$A$104,A16,ONE_OFF_EVENTS!$C$5:$C$104) -> 0 | H16: =D16-E16-F16+G16 -> -557.82341 | I16: =J15 -> 3306.1191 | J16: =I16+H16 -> 2748.2957
A17: =SETUP!$B$4+13 -> 46057 | B17: =TEXT(A17,"ddd") -> Wed | C17: =SETUP!$B$5*(1+SETUP!$B$17) -> 1500 | D17: =C17*(SETUP!$B$6+SETUP!$B$18) -> 345 | E17: =C17*(SETUP!$B$7+SETUP!$B$22) -> 525 | F17: =((SETUP!$B$8*(1+SETUP!$B$19)+SETUP!$B$9*(1+SETUP!$B$20)+SETUP!$B$10*(1+SETUP!$B$21))/SETUP!$B$14) -> 377.82341 | G17: =SUMIF(ONE_OFF_EVENTS!$A$5:$A$104,A17,ONE_OFF_EVENTS!$C$5:$C$104) -> 0 | H17: =D17-E17-F17+G17 -> -557.82341 | I17: =J16 -> 2748.2957 | J17: =I17+H17 -> 2190.4723
A18: =SETUP!$B$4+14 -> 46058 | B18: =TEXT(A18,"ddd") -> Thu | C18: =SETUP!$B$5*(1+SETUP!$B$17) -> 1500 | D18: =C18*(SETUP!$B$6+SETUP!$B$18) -> 345 | E18: =C18*(SETUP!$B$7+SETUP!$B$22) -> 525 | F18: =((SETUP!$B$8*(1+SETUP!$B$19)+SETUP!$B$9*(1+SETUP!$B$20)+SETUP!$B$10*(1+SETUP!$B$21))/SETUP!$B$14) -> 377.82341 | G18: =SUMIF(ONE_OFF_EVENTS!$A$5:$A$104,A18,ONE_OFF_EVENTS!$C$5:$C$104) -> 0 | H18: =D18-E18-F18+G18 -> -557.82341 | I18: =J17 -> 2190.4723 | J18: =I18+H18 -> 1632.6489
A19: =SETUP!$B$4+15 -> 46059 | B19: =TEXT(A19,"ddd") -> Fri | C19: =SETUP!$B$5*(1+SETUP!$B$17) -> 1500 | D19: =C19*(SETUP!$B$6+SETUP!$B$18) -> 345 | E19: =C19*(SETUP!$B$7+SETUP!$B$22) -> 525 | F19: =((SETUP!$B$8*(1+SETUP!$B$19)+SETUP!$B$9*(1+SETUP!$B$20)+SETUP!$B$10*(1+SETUP!$B$21))/SETUP!$B$14) -> 377.82341 | G19: =SUMIF(ONE_OFF_EVENTS!$A$5:$A$104,A19,ONE_OFF_EVENTS!$C$5:$C$104) -> 0 | H19: =D19-E19-F19+G19 -> -557.82341 | I19: =J18 -> 1632.6489 | J19: =I19+H19 -> 1074.8255
A20: =SETUP!$B$4+16 -> 46060 | B20: =TEXT(A20,"ddd") -> Sat | C20: =SETUP!$B$5*(1+SETUP!$B$17) -> 1500 | D20: =C20*(SETUP!$B$6+SETUP!$B$18) -> 345 | E20: =C20*(SETUP!$B$7+SETUP!$B$22) -> 525 | F20: =((SETUP!$B$8*(1+SETUP!$B$19)+SETUP!$B$9*(1+SETUP!$B$20)+SETUP!$B$10*(1+SETUP!$B$21))/SETUP!$B$14) -> 377.82341 | G20: =SUMIF(ONE_OFF_EVENTS!$A$5:$A$104,A20,ONE_OFF_EVENTS!$C$5:$C$104) -> 0 | H20: =D20-E20-F20+G20 -> -557.82341 | I20: =J19 -> 1074.8255 | J20: =I20+H20 -> 517.00205
A21: =SETUP!$B$4+17 -> 46061 | B21: =TEXT(A21,"ddd") -> Sun | C21: =SETUP!$B$5*(1+SETUP!$B$17) -> 1500 | D21: =C21*(SETUP!$B$6+SETUP!$B$18) -> 345 | E21: =C21*(SETUP!$B$7+SETUP!$B$22) -> 525 | F21: =((SETUP!$B$8*(1+SETUP!$B$19)+SETUP!$B$9*(1+SETUP!$B$20)+SETUP!$B$10*(1+SETUP!$B$21))/SETUP!$B$14) -> 377.82341 | G21: =SUMIF(ONE_OFF_EVENTS!$A$5:$A$104,A21,ONE_OFF_EVENTS!$C$5:$C$104) -> 0 | H21: =D21-E21-F21+G21 -> -557.82341 | I21: =J20 -> 517.00205 | J21: =I21+H21 -> -40.821355
A22: =SETUP!$B$4+18 -> 46062 | B22: =TEXT(A22,"ddd") -> Mon | C22: =SETUP!$B$5*(1+SETUP!$B$17) -> 1500 | D22: =C22*(SETUP!$B$6+SETUP!$B$18) -> 345 | E22: =C22*(SETUP!$B$7+SETUP!$B$22) -> 525 | F22: =((SETUP!$B$8*(1+SETUP!$B$19)+SETUP!$B$9*(1+SETUP!$B$20)+SETUP!$B$10*(1+SETUP!$B$21))/SETUP!$B$14) -> 377.82341 | G22: =SUMIF(ONE_OFF_EVENTS!$A$5:$A$104,A22,ONE_OFF_EVENTS!$C$5:$C$104) -> 0 | H22: =D22-E22-F22+G22 -> -557.82341 | I22: =J21 -> -40.821355 | J22: =I22+H22 -> -598.64476
A23: =SETUP!$B$4+19 -> 46063 | B23: =TEXT(A23,"ddd") -> Tue | C23: =SETUP!$B$5*(1+SETUP!$B$17) -> 1500 | D23: =C23*(SETUP!$B$6+SETUP!$B$18) -> 345 | E23: =C23*(SETUP!$B$7+SETUP!$B$22) -> 525 | F23: =((SETUP!$B$8*(1+SETUP!$B$19)+SETUP!$B$9*(1+SETUP!$B$20)+SETUP!$B$10*(1+SETUP!$B$21))/SETUP!$B$14) -> 377.82341 | G23: =SUMIF(ONE_OFF_EVENTS!$A$5:$A$104,A23,ONE_OFF_EVENTS!$C$5:$C$104) -> 0 | H23: =D23-E23-F23+G23 -> -557.82341 | I23: =J22 -> -598.64476 | J23: =I23+H23 -> -1156.4682
A24: =SETUP!$B$4+20 -> 46064 | B24: =TEXT(A24,"ddd") -> Wed | C24: =SETUP!$B$5*(1+SETUP!$B$17) -> 1500 | D24: =C24*(SETUP!$B$6+SETUP!$B$18) -> 345 | E24: =C24*(SETUP!$B$7+SETUP!$B$22) -> 525 | F24: =((SETUP!$B$8*(1+SETUP!$B$19)+SETUP!$B$9*(1+SETUP!$B$20)+SETUP!$B$10*(1+SETUP!$B$21))/SETUP!$B$14) -> 377.82341 | G24: =SUMIF(ONE_OFF_EVENTS!$A$5:$A$104,A24,ONE_OFF_EVENTS!$C$5:$C$104) -> 0 | H24: =D24-E24-F24+G24 -> -557.82341 | I24: =J23 -> -1156.4682 | J24: =I24+H24 -> -1714.2916
A25: =SETUP!$B$4+21 -> 46065 | B25: =TEXT(A25,"ddd") -> Thu | C25: =SETUP!$B$5*(1+SETUP!$B$17) -> 1500 | D25: =C25*(SETUP!$B$6+SETUP!$B$18) -> 345 | E25: =C25*(SETUP!$B$7+SETUP!$B$22) -> 525 | F25: =((SETUP!$B$8*(1+SETUP!$B$19)+SETUP!$B$9*(1+SETUP!$B$20)+SETUP!$B$10*(1+SETUP!$B$21))/SETUP!$B$14) -> 377.82341 | G25: =SUMIF(ONE_OFF_EVENTS!$A$5:$A$104,A25,ONE_OFF_EVENTS!$C$5:$C$104) -> 0 | H25: =D25-E25-F25+G25 -> -557.82341 | I25: =J24 -> -1714.2916 | J25: =I25+H25 -> -2272.115
A26: =SETUP!$B$4+22 -> 46066 | B26: =TEXT(A26,"ddd") -> Fri | C26: =SETUP!$B$5*(1+SETUP!$B$17) -> 1500 | D26: =C26*(SETUP!$B$6+SETUP!$B$18) -> 345 | E26: =C26*(SETUP!$B$7+SETUP!$B$22) -> 525 | F26: =((SETUP!$B$8*(1+SETUP!$B$19)+SETUP!$B$9*(1+SETUP!$B$20)+SETUP!$B$10*(1+SETUP!$B$21))/SETUP!$B$14) -> 377.82341 | G26: =SUMIF(ONE_OFF_EVENTS!$A$5:$A$104,A26,ONE_OFF_EVENTS!$C$5:$C$104) -> 0 | H26: =D26-E26-F26+G26 -> -557.82341 | I26: =J25 -> -2272.115 | J26: =I26+H26 -> -2829.9384
A27: =SETUP!$B$4+23 -> 46067 | B27: =TEXT(A27,"ddd") -> Sat | C27: =SETUP!$B$5*(1+SETUP!$B$17) -> 1500 | D27: =C27*(SETUP!$B$6+SETUP!$B$18) -> 345 | E27: =C27*(SETUP!$B$7+SETUP!$B$22) -> 525 | F27: =((SETUP!$B$8*(1+SETUP!$B$19)+SETUP!$B$9*(1+SETUP!$B$20)+SETUP!$B$10*(1+SETUP!$B$21))/SETUP!$B$14) -> 377.82341 | G27: =SUMIF(ONE_OFF_EVENTS!$A$5:$A$104,A27,ONE_OFF_EVENTS!$C$5:$C$104) -> 0 | H27: =D27-E27-F27+G27 -> -557.82341 | I27: =J26 -> -2829.9384 | J27: =I27+H27 -> -3387.7618
A28: =SETUP!$B$4+24 -> 46068 | B28: =TEXT(A28,"ddd") -> Sun | C28: =SETUP!$B$5*(1+SETUP!$B$17) -> 1500 | D28: =C28*(SETUP!$B$6+SETUP!$B$18) -> 345 | E28: =C28*(SETUP!$B$7+SETUP!$B$22) -> 525 | F28: =((SETUP!$B$8*(1+SETUP!$B$19)+SETUP!$B$9*(1+SETUP!$B$20)+SETUP!$B$10*(1+SETUP!$B$21))/SETUP!$B$14) -> 377.82341 | G28: =SUMIF(ONE_OFF_EVENTS!$A$5:$A$104,A28,ONE_OFF_EVENTS!$C$5:$C$104) -> 0 | H28: =D28-E28-F28+G28 -> -557.82341 | I28: =J27 -> -3387.7618 | J28: =I28+H28 -> -3945.5852
A29: =SETUP!$B$4+25 -> 46069 | B29: =TEXT(A29,"ddd") -> Mon | C29: =SETUP!$B$5*(1+SETUP!$B$17) -> 1500 | D29: =C29*(SETUP!$B$6+SETUP!$B$18) -> 345 | E29: =C29*(SETUP!$B$7+SETUP!$B$22) -> 525 | F29: =((SETUP!$B$8*(1+SETUP!$B$19)+SETUP!$B$9*(1+SETUP!$B$20)+SETUP!$B$10*(1+SETUP!$B$21))/SETUP!$B$14) -> 377.82341 | G29: =SUMIF(ONE_OFF_EVENTS!$A$5:$A$104,A29,ONE_OFF_EVENTS!$C$5:$C$104) -> 0 | H29: =D29-E29-F29+G29 -> -557.82341 | I29: =J28 -> -3945.5852 | J29: =I29+H29 -> -4503.4086
A30: =SETUP!$B$4+26 -> 46070 | B30: =TEXT(A30,"ddd") -> Tue | C30: =SETUP!$B$5*(1+SETUP!$B$17) -> 1500 | D30: =C30*(SETUP!$B$6+SETUP!$B$18) -> 345 | E30: =C30*(SETUP!$B$7+SETUP!$B$22) -> 525 | F30: =((SETUP!$B$8*(1+SETUP!$B$19)+SETUP!$B$9*(1+SETUP!$B$20)+SETUP!$B$10*(1+SETUP!$B$21))/SETUP!$B$14) -> 377.82341 | G30: =SUMIF(ONE_OFF_EVENTS!$A$5:$A$104,A30,ONE_OFF_EVENTS!$C$5:$C$104) -> 0 | H30: =D30-E30-F30+G30 -> -557.82341 | I30: =J29 -> -4503.4086 | J30: =I30+H30 -> -5061.232
A31: =SETUP!$B$4+27 -> 46071 | B31: =TEXT(A31,"ddd") -> Wed | C31: =SETUP!$B$5*(1+SETUP!$B$17) -> 1500 | D31: =C31*(SETUP!$B$6+SETUP!$B$18) -> 345 | E31: =C31*(SETUP!$B$7+SETUP!$B$22) -> 525 | F31: =((SETUP!$B$8*(1+SETUP!$B$19)+SETUP!$B$9*(1+SETUP!$B$20)+SETUP!$B$10*(1+SETUP!$B$21))/SETUP!$B$14) -> 377.82341 | G31: =SUMIF(ONE_OFF_EVENTS!$A$5:$A$104,A31,ONE_OFF_EVENTS!$C$5:$C$104) -> 0 | H31: =D31-E31-F31+G31 -> -557.82341 | I31: =J30 -> -5061.232 | J31: =I31+H31 -> -5619.0554
A32: =SETUP!$B$4+28 -> 46072 | B32: =TEXT(A32,"ddd") -> Thu | C32: =SETUP!$B$5*(1+SETUP!$B$17) -> 1500 | D32: =C32*(SETUP!$B$6+SETUP!$B$18) -> 345 | E32: =C32*(SETUP!$B$7+SETUP!$B$22) -> 525 | F32: =((SETUP!$B$8*(1+SETUP!$B$19)+SETUP!$B$9*(1+SETUP!$B$20)+SETUP!$B$10*(1+SETUP!$B$21))/SETUP!$B$14) -> 377.82341 | G32: =SUMIF(ONE_OFF_EVENTS!$A$5:$A$104,A32,ONE_OFF_EVENTS!$C$5:$C$104) -> 0 | H32: =D32-E32-F32+G32 -> -557.82341 | I32: =J31 -> -5619.0554 | J32: =I32+H32 -> -6176.8789
A33: =SETUP!$B$4+29 -> 46073 | B33: =TEXT(A33,"ddd") -> Fri | C33: =SETUP!$B$5*(1+SETUP!$B$17) -> 1500 | D33: =C33*(SETUP!$B$6+SETUP!$B$18) -> 345 | E33: =C33*(SETUP!$B$7+SETUP!$B$22) -> 525 | F33: =((SETUP!$B$8*(1+SETUP!$B$19)+SETUP!$B$9*(1+SETUP!$B$20)+SETUP!$B$10*(1+SETUP!$B$21))/SETUP!$B$14) -> 377.82341 | G33: =SUMIF(ONE_OFF_EVENTS!$A$5:$A$104,A33,ONE_OFF_EVENTS!$C$5:$C$104) -> 0 | H33: =D33-E33-F33+G33 -> -557.82341 | I33: =J32 -> -6176.8789 | J33: =I33+H33 -> -6734.7023
A34: =SETUP!$B$4+30 -> 46074 | B34: =TEXT(A34,"ddd") -> Sat | C34: =SETUP!$B$5*(1+SETUP!$B$17) -> 1500 | D34: =C34*(SETUP!$B$6+SETUP!$B$18) -> 345 | E34: =C34*(SETUP!$B$7+SETUP!$B$22) -> 525 | F34: =((SETUP!$B$8*(1+SETUP!$B$19)+SETUP!$B$9*(1+SETUP!$B$20)+SETUP!$B$10*(1+SETUP!$B$21))/SETUP!$B$14) -> 377.82341 | G34: =SUMIF(ONE_OFF_EVENTS!$A$5:$A$104,A34,ONE_OFF_EVENTS!$C$5:$C$104) -> 0 | H34: =D34-E34-F34+G34 -> -557.82341 | I34: =J33 -> -6734.7023 | J34: =I34+H34 -> -7292.5257
A35: =SETUP!$B$4+31 -> 46075 | B35: =TEXT(A35,"ddd") -> Sun | C35: =SETUP!$B$5*(1+SETUP!$B$17) -> 1500 | D35: =C35*(SETUP!$B$6+SETUP!$B$18) -> 345 | E35: =C35*(SETUP!$B$7+SETUP!$B$22) -> 525 | F35: =((SETUP!$B$8*(1+SETUP!$B$19)+SETUP!$B$9*(1+SETUP!$B$20)+SETUP!$B$10*(1+SETUP!$B$21))/SETUP!$B$14) -> 377.82341 | G35: =SUMIF(ONE_OFF_EVENTS!$A$5:$A$104,A35,ONE_OFF_EVENTS!$C$5:$C$104) -> 0 | H35: =D35-E35-F35+G35 -> -557.82341 | I35: =J34 -> -7292.5257 | J35: =I35+H35 -> -7850.3491
A36: =SETUP!$B$4+32 -> 46076 | B36: =TEXT(A36,"ddd") -> Mon | C36: =SETUP!$B$5*(1+SETUP!$B$17) -> 1500 | D36: =C36*(SETUP!$B$6+SETUP!$B$18) -> 345 | E36: =C36*(SETUP!$B$7+SETUP!$B$22) -> 525 | F36: =((SETUP!$B$8*(1+SETUP!$B$19)+SETUP!$B$9*(1+SETUP!$B$20)+SETUP!$B$10*(1+SETUP!$B$21))/SETUP!$B$14) -> 377.82341 | G36: =SUMIF(ONE_OFF_EVENTS!$A$5:$A$104,A36,ONE_OFF_EVENTS!$C$5:$C$104) -> 0 | H36: =D36-E36-F36+G36 -> -557.82341 | I36: =J35 -> -7850.3491 | J36: =I36+H36 -> -8408.1725
A37: =SETUP!$B$4+33 -> 46077 | B37: =TEXT(A37,"ddd") -> Tue | C37: =SETUP!$B$5*(1+SETUP!$B$17) -> 1500 | D37: =C37*(SETUP!$B$6+SETUP!$B$18) -> 345 | E37: =C37*(SETUP!$B$7+SETUP!$B$22) -> 525 | F37: =((SETUP!$B$8*(1+SETUP!$B$19)+SETUP!$B$9*(1+SETUP!$B$20)+SETUP!$B$10*(1+SETUP!$B$21))/SETUP!$B$14) -> 377.82341 | G37: =SUMIF(ONE_OFF_EVENTS!$A$5:$A$104,A37,ONE_OFF_EVENTS!$C$5:$C$104) -> 0 | H37: =D37-E37-F37+G37 -> -557.82341 | I37: =J36 -> -8408.1725 | J37: =I37+H37 -> -8965.9959
A38: =SETUP!$B$4+34 -> 46078 | B38: =TEXT(A38,"ddd") -> Wed | C38: =SETUP!$B$5*(1+SETUP!$B$17) -> 1500 | D38: =C38*(SETUP!$B$6+SETUP!$B$18) -> 345 | E38: =C38*(SETUP!$B$7+SETUP!$B$22) -> 525 | F38: =((SETUP!$B$8*(1+SETUP!$B$19)+SETUP!$B$9*(1+SETUP!$B$20)+SETUP!$B$10*(1+SETUP!$B$21))/SETUP!$B$14) -> 377.82341 | G38: =SUMIF(ONE_OFF_EVENTS!$A$5:$A$104,A38,ONE_OFF_EVENTS!$C$5:$C$104) -> 0 | H38: =D38-E38-F38+G38 -> -557.82341 | I38: =J37 -> -8965.9959 | J38: =I38+H38 -> -9523.8193
A39: =SETUP!$B$4+35 -> 46079 | B39: =TEXT(A39,"ddd") -> Thu | C39: =SETUP!$B$5*(1+SETUP!$B$17) -> 1500 | D39: =C39*(SETUP!$B$6+SETUP!$B$18) -> 345 | E39: =C39*(SETUP!$B$7+SETUP!$B$22) -> 525 | F39: =((SETUP!$B$8*(1+SETUP!$B$19)+SETUP!$B$9*(1+SETUP!$B$20)+SETUP!$B$10*(1+SETUP!$B$21))/SETUP!$B$14) -> 377.82341 | G39: =SUMIF(ONE_OFF_EVENTS!$A$5:$A$104,A39,ONE_OFF_EVENTS!$C$5:$C$104) -> 0 | H39: =D39-E39-F39+G39 -> -557.82341 | I39: =J38 -> -9523.8193 | J39: =I39+H39 -> -10081.643
A40: =SETUP!$B$4+36 -> 46080 | B40: =TEXT(A40,"ddd") -> Fri | C40: =SETUP!$B$5*(1+SETUP!$B$17) -> 1500 | D40: =C40*(SETUP!$B$6+SETUP!$B$18) -> 345 | E40: =C40*(SETUP!$B$7+SETUP!$B$22) -> 525 | F40: =((SETUP!$B$8*(1+SETUP!$B$19)+SETUP!$B$9*(1+SETUP!$B$20)+SETUP!$B$10*(1+SETUP!$B$21))/SETUP!$B$14) -> 377.82341 | G40: =SUMIF(ONE_OFF_EVENTS!$A$5:$A$104,A40,ONE_OFF_EVENTS!$C$5:$C$104) -> 0 | H40: =D40-E40-F40+G40 -> -557.82341 | I40: =J39 -> -10081.643 | J40: =I40+H40 -> -10639.466
A41: =SETUP!$B$4+37 -> 46081 | B41: =TEXT(A41,"ddd") -> Sat | C41: =SETUP!$B$5*(1+SETUP!$B$17) -> 1500 | D41: =C41*(SETUP!$B$6+SETUP!$B$18) -> 345 | E41: =C41*(SETUP!$B$7+SETUP!$B$22) -> 525 | F41: =((SETUP!$B$8*(1+SETUP!$B$19)+SETUP!$B$9*(1+SETUP!$B$20)+SETUP!$B$10*(1+SETUP!$B$21))/SETUP!$B$14) -> 377.82341 | G41: =SUMIF(ONE_OFF_EVENTS!$A$5:$A$104,A41,ONE_OFF_EVENTS!$C$5:$C$104) -> 0 | H41: =D41-E41-F41+G41 -> -557.82341 | I41: =J40 -> -10639.466 | J41: =I41+H41 -> -11197.29
A42: =SETUP!$B$4+38 -> 46082 | B42: =TEXT(A42,"ddd") -> Sun | C42: =SETUP!$B$5*(1+SETUP!$B$17) -> 1500 | D42: =C42*(SETUP!$B$6+SETUP!$B$18) -> 345 | E42: =C42*(SETUP!$B$7+SETUP!$B$22) -> 525 | F42: =((SETUP!$B$8*(1+SETUP!$B$19)+SETUP!$B$9*(1+SETUP!$B$20)+SETUP!$B$10*(1+SETUP!$B$21))/SETUP!$B$14) -> 377.82341 | G42: =SUMIF(ONE_OFF_EVENTS!$A$5:$A$104,A42,ONE_OFF_EVENTS!$C$5:$C$104) -> 0 | H42: =D42-E42-F42+G42 -> -557.82341 | I42: =J41 -> -11197.29 | J42: =I42+H42 -> -11755.113
A43: =SETUP!$B$4+39 -> 46083 | B43: =TEXT(A43,"ddd") -> Mon | C43: =SETUP!$B$5*(1+SETUP!$B$17) -> 1500 | D43: =C43*(SETUP!$B$6+SETUP!$B$18) -> 345 | E43: =C43*(SETUP!$B$7+SETUP!$B$22) -> 525 | F43: =((SETUP!$B$8*(1+SETUP!$B$19)+SETUP!$B$9*(1+SETUP!$B$20)+SETUP!$B$10*(1+SETUP!$B$21))/SETUP!$B$14) -> 377.82341 | G43: =SUMIF(ONE_OFF_EVENTS!$A$5:$A$104,A43,ONE_OFF_EVENTS!$C$5:$C$104) -> 0 | H43: =D43-E43-F43+G43 -> -557.82341 | I43: =J42 -> -11755.113 | J43: =I43+H43 -> -12312.936
A44: =SETUP!$B$4+40 -> 46084 | B44: =TEXT(A44,"ddd") -> Tue | C44: =SETUP!$B$5*(1+SETUP!$B$17) -> 1500 | D44: =C44*(SETUP!$B$6+SETUP!$B$18) -> 345 | E44: =C44*(SETUP!$B$7+SETUP!$B$22) -> 525 | F44: =((SETUP!$B$8*(1+SETUP!$B$19)+SETUP!$B$9*(1+SETUP!$B$20)+SETUP!$B$10*(1+SETUP!$B$21))/SETUP!$B$14) -> 377.82341 | G44: =SUMIF(ONE_OFF_EVENTS!$A$5:$A$104,A44,ONE_OFF_EVENTS!$C$5:$C$104) -> 0 | H44: =D44-E44-F44+G44 -> -557.82341 | I44: =J43 -> -12312.936 | J44: =I44+H44 -> -12870.76
A45: =SETUP!$B$4+41 -> 46085 | B45: =TEXT(A45,"ddd") -> Wed | C45: =SETUP!$B$5*(1+SETUP!$B$17) -> 1500 | D45: =C45*(SETUP!$B$6+SETUP!$B$18) -> 345 | E45: =C45*(SETUP!$B$7+SETUP!$B$22) -> 525 | F45: =((SETUP!$B$8*(1+SETUP!$B$19)+SETUP!$B$9*(1+SETUP!$B$20)+SETUP!$B$10*(1+SETUP!$B$21))/SETUP!$B$14) -> 377.82341 | G45: =SUMIF(ONE_OFF_EVENTS!$A$5:$A$104,A45,ONE_OFF_EVENTS!$C$5:$C$104) -> 0 | H45: =D45-E45-F45+G45 -> -557.82341 | I45: =J44 -> -12870.76 | J45: =I45+H45 -> -13428.583
A46: =SETUP!$B$4+42 -> 46086 | B46: =TEXT(A46,"ddd") -> Thu | C46: =SETUP!$B$5*(1+SETUP!$B$17) -> 1500 | D46: =C46*(SETUP!$B$6+SETUP!$B$18) -> 345 | E46: =C46*(SETUP!$B$7+SETUP!$B$22) -> 525 | F46: =((SETUP!$B$8*(1+SETUP!$B$19)+SETUP!$B$9*(1+SETUP!$B$20)+SETUP!$B$10*(1+SETUP!$B$21))/SETUP!$B$14) -> 377.82341 | G46: =SUMIF(ONE_OFF_EVENTS!$A$5:$A$104,A46,ONE_OFF_EVENTS!$C$5:$C$104) -> 0 | H46: =D46-E46-F46+G46 -> -557.82341 | I46: =J45 -> -13428.583 | J46: =I46+H46 -> -13986.407
A47: =SETUP!$B$4+43 -> 46087 | B47: =TEXT(A47,"ddd") -> Fri | C47: =SETUP!$B$5*(1+SETUP!$B$17) -> 1500 | D47: =C47*(SETUP!$B$6+SETUP!$B$18) -> 345 | E47: =C47*(SETUP!$B$7+SETUP!$B$22) -> 525 | F47: =((SETUP!$B$8*(1+SETUP!$B$19)+SETUP!$B$9*(1+SETUP!$B$20)+SETUP!$B$10*(1+SETUP!$B$21))/SETUP!$B$14) -> 377.82341 | G47: =SUMIF(ONE_OFF_EVENTS!$A$5:$A$104,A47,ONE_OFF_EVENTS!$C$5:$C$104) -> 0 | H47: =D47-E47-F47+G47 -> -557.82341 | I47: =J46 -> -13986.407 | J47: =I47+H47 -> -14544.23
A48: =SETUP!$B$4+44 -> 46088 | B48: =TEXT(A48,"ddd") -> Sat | C48: =SETUP!$B$5*(1+SETUP!$B$17) -> 1500 | D48: =C48*(SETUP!$B$6+SETUP!$B$18) -> 345 | E48: =C48*(SETUP!$B$7+SETUP!$B$22) -> 525 | F48: =((SETUP!$B$8*(1+SETUP!$B$19)+SETUP!$B$9*(1+SETUP!$B$20)+SETUP!$B$10*(1+SETUP!$B$21))/SETUP!$B$14) -> 377.82341 | G48: =SUMIF(ONE_OFF_EVENTS!$A$5:$A$104,A48,ONE_OFF_EVENTS!$C$5:$C$104) -> 0 | H48: =D48-E48-F48+G48 -> -557.82341 | I48: =J47 -> -14544.23 | J48: =I48+H48 -> -15102.053
A49: =SETUP!$B$4+45 -> 46089 | B49: =TEXT(A49,"ddd") -> Sun | C49: =SETUP!$B$5*(1+SETUP!$B$17) -> 1500 | D49: =C49*(SETUP!$B$6+SETUP!$B$18) -> 345 | E49: =C49*(SETUP!$B$7+SETUP!$B$22) -> 525 | F49: =((SETUP!$B$8*(1+SETUP!$B$19)+SETUP!$B$9*(1+SETUP!$B$20)+SETUP!$B$10*(1+SETUP!$B$21))/SETUP!$B$14) -> 377.82341 | G49: =SUMIF(ONE_OFF_EVENTS!$A$5:$A$104,A49,ONE_OFF_EVENTS!$C$5:$C$104) -> 0 | H49: =D49-E49-F49+G49 -> -557.82341 | I49: =J48 -> -15102.053 | J49: =I49+H49 -> -15659.877
A50: =SETUP!$B$4+46 -> 46090 | B50: =TEXT(A50,"ddd") -> Mon | C50: =SETUP!$B$5*(1+SETUP!$B$17) -> 1500 | D50: =C50*(SETUP!$B$6+SETUP!$B$18) -> 345 | E50: =C50*(SETUP!$B$7+SETUP!$B$22) -> 525 | F50: =((SETUP!$B$8*(1+SETUP!$B$19)+SETUP!$B$9*(1+SETUP!$B$20)+SETUP!$B$10*(1+SETUP!$B$21))/SETUP!$B$14) -> 377.82341 | G50: =SUMIF(ONE_OFF_EVENTS!$A$5:$A$104,A50,ONE_OFF_EVENTS!$C$5:$C$104) -> 0 | H50: =D50-E50-F50+G50 -> -557.82341 | I50: =J49 -> -15659.877 | J50: =I50+H50 -> -16217.7
A51: =SETUP!$B$4+47 -> 46091 | B51: =TEXT(A51,"ddd") -> Tue | C51: =SETUP!$B$5*(1+SETUP!$B$17) -> 1500 | D51: =C51*(SETUP!$B$6+SETUP!$B$18) -> 345 | E51: =C51*(SETUP!$B$7+SETUP!$B$22) -> 525 | F51: =((SETUP!$B$8*(1+SETUP!$B$19)+SETUP!$B$9*(1+SETUP!$B$20)+SETUP!$B$10*(1+SETUP!$B$21))/SETUP!$B$14) -> 377.82341 | G51: =SUMIF(ONE_OFF_EVENTS!$A$5:$A$104,A51,ONE_OFF_EVENTS!$C$5:$C$104) -> 0 | H51: =D51-E51-F51+G51 -> -557.82341 | I51: =J50 -> -16217.7 | J51: =I51+H51 -> -16775.524
A52: =SETUP!$B$4+48 -> 46092 | B52: =TEXT(A52,"ddd") -> Wed | C52: =SETUP!$B$5*(1+SETUP!$B$17) -> 1500 | D52: =C52*(SETUP!$B$6+SETUP!$B$18) -> 345 | E52: =C52*(SETUP!$B$7+SETUP!$B$22) -> 525 | F52: =((SETUP!$B$8*(1+SETUP!$B$19)+SETUP!$B$9*(1+SETUP!$B$20)+SETUP!$B$10*(1+SETUP!$B$21))/SETUP!$B$14) -> 377.82341 | G52: =SUMIF(ONE_OFF_EVENTS!$A$5:$A$104,A52,ONE_OFF_EVENTS!$C$5:$C$104) -> 0 | H52: =D52-E52-F52+G52 -> -557.82341 | I52: =J51 -> -16775.524 | J52: =I52+H52 -> -17333.347
A53: =SETUP!$B$4+49 -> 46093 | B53: =TEXT(A53,"ddd") -> Thu | C53: =SETUP!$B$5*(1+SETUP!$B$17) -> 1500 | D53: =C53*(SETUP!$B$6+SETUP!$B$18) -> 345 | E53: =C53*(SETUP!$B$7+SETUP!$B$22) -> 525 | F53: =((SETUP!$B$8*(1+SETUP!$B$19)+SETUP!$B$9*(1+SETUP!$B$20)+SETUP!$B$10*(1+SETUP!$B$21))/SETUP!$B$14) -> 377.82341 | G53: =SUMIF(ONE_OFF_EVENTS!$A$5:$A$104,A53,ONE_OFF_EVENTS!$C$5:$C$104) -> 0 | H53: =D53-E53-F53+G53 -> -557.82341 | I53: =J52 -> -17333.347 | J53: =I53+H53 -> -17891.17
A54: =SETUP!$B$4+50 -> 46094 | B54: =TEXT(A54,"ddd") -> Fri | C54: =SETUP!$B$5*(1+SETUP!$B$17) -> 1500 | D54: =C54*(SETUP!$B$6+SETUP!$B$18) -> 345 | E54: =C54*(SETUP!$B$7+SETUP!$B$22) -> 525 | F54: =((SETUP!$B$8*(1+SETUP!$B$19)+SETUP!$B$9*(1+SETUP!$B$20)+SETUP!$B$10*(1+SETUP!$B$21))/SETUP!$B$14) -> 377.82341 | G54: =SUMIF(ONE_OFF_EVENTS!$A$5:$A$104,A54,ONE_OFF_EVENTS!$C$5:$C$104) -> 0 | H54: =D54-E54-F54+G54 -> -557.82341 | I54: =J53 -> -17891.17 | J54: =I54+H54 -> -18448.994
A55: =SETUP!$B$4+51 -> 46095 | B55: =TEXT(A55,"ddd") -> Sat | C55: =SETUP!$B$5*(1+SETUP!$B$17) -> 1500 | D55: =C55*(SETUP!$B$6+SETUP!$B$18) -> 345 | E55: =C55*(SETUP!$B$7+SETUP!$B$22) -> 525 | F55: =((SETUP!$B$8*(1+SETUP!$B$19)+SETUP!$B$9*(1+SETUP!$B$20)+SETUP!$B$10*(1+SETUP!$B$21))/SETUP!$B$14) -> 377.82341 | G55: =SUMIF(ONE_OFF_EVENTS!$A$5:$A$104,A55,ONE_OFF_EVENTS!$C$5:$C$104) -> 0 | H55: =D55-E55-F55+G55 -> -557.82341 | I55: =J54 -> -18448.994 | J55: =I55+H55 -> -19006.817
A56: =SETUP!$B$4+52 -> 46096 | B56: =TEXT(A56,"ddd") -> Sun | C56: =SETUP!$B$5*(1+SETUP!$B$17) -> 1500 | D56: =C56*(SETUP!$B$6+SETUP!$B$18) -> 345 | E56: =C56*(SETUP!$B$7+SETUP!$B$22) -> 525 | F56: =((SETUP!$B$8*(1+SETUP!$B$19)+SETUP!$B$9*(1+SETUP!$B$20)+SETUP!$B$10*(1+SETUP!$B$21))/SETUP!$B$14) -> 377.82341 | G56: =SUMIF(ONE_OFF_EVENTS!$A$5:$A$104,A56,ONE_OFF_EVENTS!$C$5:$C$104) -> 0 | H56: =D56-E56-F56+G56 -> -557.82341 | I56: =J55 -> -19006.817 | J56: =I56+H56 -> -19564.641
A57: =SETUP!$B$4+53 -> 46097 | B57: =TEXT(A57,"ddd") -> Mon | C57: =SETUP!$B$5*(1+SETUP!$B$17) -> 1500 | D57: =C57*(SETUP!$B$6+SETUP!$B$18) -> 345 | E57: =C57*(SETUP!$B$7+SETUP!$B$22) -> 525 | F57: =((SETUP!$B$8*(1+SETUP!$B$19)+SETUP!$B$9*(1+SETUP!$B$20)+SETUP!$B$10*(1+SETUP!$B$21))/SETUP!$B$14) -> 377.82341 | G57: =SUMIF(ONE_OFF_EVENTS!$A$5:$A$104,A57,ONE_OFF_EVENTS!$C$5:$C$104) -> 0 | H57: =D57-E57-F57+G57 -> -557.82341 | I57: =J56 -> -19564.641 | J57: =I57+H57 -> -20122.464
A58: =SETUP!$B$4+54 -> 46098 | B58: =TEXT(A58,"ddd") -> Tue | C58: =SETUP!$B$5*(1+SETUP!$B$17) -> 1500 | D58: =C58*(SETUP!$B$6+SETUP!$B$18) -> 345 | E58: =C58*(SETUP!$B$7+SETUP!$B$22) -> 525 | F58: =((SETUP!$B$8*(1+SETUP!$B$19)+SETUP!$B$9*(1+SETUP!$B$20)+SETUP!$B$10*(1+SETUP!$B$21))/SETUP!$B$14) -> 377.82341 | G58: =SUMIF(ONE_OFF_EVENTS!$A$5:$A$104,A58,ONE_OFF_EVENTS!$C$5:$C$104) -> 0 | H58: =D58-E58-F58+G58 -> -557.82341 | I58: =J57 -> -20122.464 | J58: =I58+H58 -> -20680.287
A59: =SETUP!$B$4+55 -> 46099 | B59: =TEXT(A59,"ddd") -> Wed | C59: =SETUP!$B$5*(1+SETUP!$B$17) -> 1500 | D59: =C59*(SETUP!$B$6+SETUP!$B$18) -> 345 | E59: =C59*(SETUP!$B$7+SETUP!$B$22) -> 525 | F59: =((SETUP!$B$8*(1+SETUP!$B$19)+SETUP!$B$9*(1+SETUP!$B$20)+SETUP!$B$10*(1+SETUP!$B$21))/SETUP!$B$14) -> 377.82341 | G59: =SUMIF(ONE_OFF_EVENTS!$A$5:$A$104,A59,ONE_OFF_EVENTS!$C$5:$C$104) -> 0 | H59: =D59-E59-F59+G59 -> -557.82341 | I59: =J58 -> -20680.287 | J59: =I59+H59 -> -21238.111
A60: =SETUP!$B$4+56 -> 46100 | B60: =TEXT(A60,"ddd") -> Thu | C60: =SETUP!$B$5*(1+SETUP!$B$17) -> 1500 | D60: =C60*(SETUP!$B$6+SETUP!$B$18) -> 345 | E60: =C60*(SETUP!$B$7+SETUP!$B$22) -> 525 | F60: =((SETUP!$B$8*(1+SETUP!$B$19)+SETUP!$B$9*(1+SETUP!$B$20)+SETUP!$B$10*(1+SETUP!$B$21))/SETUP!$B$14) -> 377.82341 | G60: =SUMIF(ONE_OFF_EVENTS!$A$5:$A$104,A60,ONE_OFF_EVENTS!$C$5:$C$104) -> 0 | H60: =D60-E60-F60+G60 -> -557.82341 | I60: =J59 -> -21238.111 | J60: =I60+H60 -> -21795.934
A61: =SETUP!$B$4+57 -> 46101 | B61: =TEXT(A61,"ddd") -> Fri | C61: =SETUP!$B$5*(1+SETUP!$B$17) -> 1500 | D61: =C61*(SETUP!$B$6+SETUP!$B$18) -> 345 | E61: =C61*(SETUP!$B$7+SETUP!$B$22) -> 525 | F61: =((SETUP!$B$8*(1+SETUP!$B$19)+SETUP!$B$9*(1+SETUP!$B$20)+SETUP!$B$10*(1+SETUP!$B$21))/SETUP!$B$14) -> 377.82341 | G61: =SUMIF(ONE_OFF_EVENTS!$A$5:$A$104,A61,ONE_OFF_EVENTS!$C$5:$C$104) -> 0 | H61: =D61-E61-F61+G61 -> -557.82341 | I61: =J60 -> -21795.934 | J61: =I61+H61 -> -22353.758
A62: =SETUP!$B$4+58 -> 46102 | B62: =TEXT(A62,"ddd") -> Sat | C62: =SETUP!$B$5*(1+SETUP!$B$17) -> 1500 | D62: =C62*(SETUP!$B$6+SETUP!$B$18) -> 345 | E62: =C62*(SETUP!$B$7+SETUP!$B$22) -> 525 | F62: =((SETUP!$B$8*(1+SETUP!$B$19)+SETUP!$B$9*(1+SETUP!$B$20)+SETUP!$B$10*(1+SETUP!$B$21))/SETUP!$B$14) -> 377.82341 | G62: =SUMIF(ONE_OFF_EVENTS!$A$5:$A$104,A62,ONE_OFF_EVENTS!$C$5:$C$104) -> 0 | H62: =D62-E62-F62+G62 -> -557.82341 | I62: =J61 -> -22353.758 | J62: =I62+H62 -> -22911.581
A63: =SETUP!$B$4+59 -> 46103 | B63: =TEXT(A63,"ddd") -> Sun | C63: =SETUP!$B$5*(1+SETUP!$B$17) -> 1500 | D63: =C63*(SETUP!$B$6+SETUP!$B$18) -> 345 | E63: =C63*(SETUP!$B$7+SETUP!$B$22) -> 525 | F63: =((SETUP!$B$8*(1+SETUP!$B$19)+SETUP!$B$9*(1+SETUP!$B$20)+SETUP!$B$10*(1+SETUP!$B$21))/SETUP!$B$14) -> 377.82341 | G63: =SUMIF(ONE_OFF_EVENTS!$A$5:$A$104,A63,ONE_OFF_EVENTS!$C$5:$C$104) -> 0 | H63: =D63-E63-F63+G63 -> -557.82341 | I63: =J62 -> -22911.581 | J63: =I63+H63 -> -23469.405
A64: =SETUP!$B$4+60 -> 46104 | B64: =TEXT(A64,"ddd") -> Mon | C64: =SETUP!$B$5*(1+SETUP!$B$17) -> 1500 | D64: =C64*(SETUP!$B$6+SETUP!$B$18) -> 345 | E64: =C64*(SETUP!$B$7+SETUP!$B$22) -> 525 | F64: =((SETUP!$B$8*(1+SETUP!$B$19)+SETUP!$B$9*(1+SETUP!$B$20)+SETUP!$B$10*(1+SETUP!$B$21))/SETUP!$B$14) -> 377.82341 | G64: =SUMIF(ONE_OFF_EVENTS!$A$5:$A$104,A64,ONE_OFF_EVENTS!$C$5:$C$104) -> 0 | H64: =D64-E64-F64+G64 -> -557.82341 | I64: =J63 -> -23469.405 | J64: =I64+H64 -> -24027.228
A65: =SETUP!$B$4+61 -> 46105 | B65: =TEXT(A65,"ddd") -> Tue | C65: =SETUP!$B$5*(1+SETUP!$B$17) -> 1500 | D65: =C65*(SETUP!$B$6+SETUP!$B$18) -> 345 | E65: =C65*(SETUP!$B$7+SETUP!$B$22) -> 525 | F65: =((SETUP!$B$8*(1+SETUP!$B$19)+SETUP!$B$9*(1+SETUP!$B$20)+SETUP!$B$10*(1+SETUP!$B$21))/SETUP!$B$14) -> 377.82341 | G65: =SUMIF(ONE_OFF_EVENTS!$A$5:$A$104,A65,ONE_OFF_EVENTS!$C$5:$C$104) -> 0 | H65: =D65-E65-F65+G65 -> -557.82341 | I65: =J64 -> -24027.228 | J65: =I65+H65 -> -24585.051
A66: =SETUP!$B$4+62 -> 46106 | B66: =TEXT(A66,"ddd") -> Wed | C66: =SETUP!$B$5*(1+SETUP!$B$17) -> 1500 | D66: =C66*(SETUP!$B$6+SETUP!$B$18) -> 345 | E66: =C66*(SETUP!$B$7+SETUP!$B$22) -> 525 | F66: =((SETUP!$B$8*(1+SETUP!$B$19)+SETUP!$B$9*(1+SETUP!$B$20)+SETUP!$B$10*(1+SETUP!$B$21))/SETUP!$B$14) -> 377.82341 | G66: =SUMIF(ONE_OFF_EVENTS!$A$5:$A$104,A66,ONE_OFF_EVENTS!$C$5:$C$104) -> 0 | H66: =D66-E66-F66+G66 -> -557.82341 | I66: =J65 -> -24585.051 | J66: =I66+H66 -> -25142.875
A67: =SETUP!$B$4+63 -> 46107 | B67: =TEXT(A67,"ddd") -> Thu | C67: =SETUP!$B$5*(1+SETUP!$B$17) -> 1500 | D67: =C67*(SETUP!$B$6+SETUP!$B$18) -> 345 | E67: =C67*(SETUP!$B$7+SETUP!$B$22) -> 525 | F67: =((SETUP!$B$8*(1+SETUP!$B$19)+SETUP!$B$9*(1+SETUP!$B$20)+SETUP!$B$10*(1+SETUP!$B$21))/SETUP!$B$14) -> 377.82341 | G67: =SUMIF(ONE_OFF_EVENTS!$A$5:$A$104,A67,ONE_OFF_EVENTS!$C$5:$C$104) -> 0 | H67: =D67-E67-F67+G67 -> -557.82341 | I67: =J66 -> -25142.875 | J67: =I67+H67 -> -25700.698
A68: =SETUP!$B$4+64 -> 46108 | B68: =TEXT(A68,"ddd") -> Fri | C68: =SETUP!$B$5*(1+SETUP!$B$17) -> 1500 | D68: =C68*(SETUP!$B$6+SETUP!$B$18) -> 345 | E68: =C68*(SETUP!$B$7+SETUP!$B$22) -> 525 | F68: =((SETUP!$B$8*(1+SETUP!$B$19)+SETUP!$B$9*(1+SETUP!$B$20)+SETUP!$B$10*(1+SETUP!$B$21))/SETUP!$B$14) -> 377.82341 | G68: =SUMIF(ONE_OFF_EVENTS!$A$5:$A$104,A68,ONE_OFF_EVENTS!$C$5:$C$104) -> 0 | H68: =D68-E68-F68+G68 -> -557.82341 | I68: =J67 -> -25700.698 | J68: =I68+H68 -> -26258.522
A69: =SETUP!$B$4+65 -> 46109 | B69: =TEXT(A69,"ddd") -> Sat | C69: =SETUP!$B$5*(1+SETUP!$B$17) -> 1500 | D69: =C69*(SETUP!$B$6+SETUP!$B$18) -> 345 | E69: =C69*(SETUP!$B$7+SETUP!$B$22) -> 525 | F69: =((SETUP!$B$8*(1+SETUP!$B$19)+SETUP!$B$9*(1+SETUP!$B$20)+SETUP!$B$10*(1+SETUP!$B$21))/SETUP!$B$14) -> 377.82341 | G69: =SUMIF(ONE_OFF_EVENTS!$A$5:$A$104,A69,ONE_OFF_EVENTS!$C$5:$C$104) -> 0 | H69: =D69-E69-F69+G69 -> -557.82341 | I69: =J68 -> -26258.522 | J69: =I69+H69 -> -26816.345
A70: =SETUP!$B$4+66 -> 46110 | B70: =TEXT(A70,"ddd") -> Sun | C70: =SETUP!$B$5*(1+SETUP!$B$17) -> 1500 | D70: =C70*(SETUP!$B$6+SETUP!$B$18) -> 345 | E70: =C70*(SETUP!$B$7+SETUP!$B$22) -> 525 | F70: =((SETUP!$B$8*(1+SETUP!$B$19)+SETUP!$B$9*(1+SETUP!$B$20)+SETUP!$B$10*(1+SETUP!$B$21))/SETUP!$B$14) -> 377.82341 | G70: =SUMIF(ONE_OFF_EVENTS!$A$5:$A$104,A70,ONE_OFF_EVENTS!$C$5:$C$104) -> 0 | H70: =D70-E70-F70+G70 -> -557.82341 | I70: =J69 -> -26816.345 | J70: =I70+H70 -> -27374.168
A71: =SETUP!$B$4+67 -> 46111 | B71: =TEXT(A71,"ddd") -> Mon | C71: =SETUP!$B$5*(1+SETUP!$B$17) -> 1500 | D71: =C71*(SETUP!$B$6+SETUP!$B$18) -> 345 | E71: =C71*(SETUP!$B$7+SETUP!$B$22) -> 525 | F71: =((SETUP!$B$8*(1+SETUP!$B$19)+SETUP!$B$9*(1+SETUP!$B$20)+SETUP!$B$10*(1+SETUP!$B$21))/SETUP!$B$14) -> 377.82341 | G71: =SUMIF(ONE_OFF_EVENTS!$A$5:$A$104,A71,ONE_OFF_EVENTS!$C$5:$C$104) -> 0 | H71: =D71-E71-F71+G71 -> -557.82341 | I71: =J70 -> -27374.168 | J71: =I71+H71 -> -27931.992
A72: =SETUP!$B$4+68 -> 46112 | B72: =TEXT(A72,"ddd") -> Tue | C72: =SETUP!$B$5*(1+SETUP!$B$17) -> 1500 | D72: =C72*(SETUP!$B$6+SETUP!$B$18) -> 345 | E72: =C72*(SETUP!$B$7+SETUP!$B$22) -> 525 | F72: =((SETUP!$B$8*(1+SETUP!$B$19)+SETUP!$B$9*(1+SETUP!$B$20)+SETUP!$B$10*(1+SETUP!$B$21))/SETUP!$B$14) -> 377.82341 | G72: =SUMIF(ONE_OFF_EVENTS!$A$5:$A$104,A72,ONE_OFF_EVENTS!$C$5:$C$104) -> 0 | H72: =D72-E72-F72+G72 -> -557.82341 | I72: =J71 -> -27931.992 | J72: =I72+H72 -> -28489.815
A73: =SETUP!$B$4+69 -> 46113 | B73: =TEXT(A73,"ddd") -> Wed | C73: =SETUP!$B$5*(1+SETUP!$B$17) -> 1500 | D73: =C73*(SETUP!$B$6+SETUP!$B$18) -> 345 | E73: =C73*(SETUP!$B$7+SETUP!$B$22) -> 525 | F73: =((SETUP!$B$8*(1+SETUP!$B$19)+SETUP!$B$9*(1+SETUP!$B$20)+SETUP!$B$10*(1+SETUP!$B$21))/SETUP!$B$14) -> 377.82341 | G73: =SUMIF(ONE_OFF_EVENTS!$A$5:$A$104,A73,ONE_OFF_EVENTS!$C$5:$C$104) -> 0 | H73: =D73-E73-F73+G73 -> -557.82341 | I73: =J72 -> -28489.815 | J73: =I73+H73 -> -29047.639
A74: =SETUP!$B$4+70 -> 46114 | B74: =TEXT(A74,"ddd") -> Thu | C74: =SETUP!$B$5*(1+SETUP!$B$17) -> 1500 | D74: =C74*(SETUP!$B$6+SETUP!$B$18) -> 345 | E74: =C74*(SETUP!$B$7+SETUP!$B$22) -> 525 | F74: =((SETUP!$B$8*(1+SETUP!$B$19)+SETUP!$B$9*(1+SETUP!$B$20)+SETUP!$B$10*(1+SETUP!$B$21))/SETUP!$B$14) -> 377.82341 | G74: =SUMIF(ONE_OFF_EVENTS!$A$5:$A$104,A74,ONE_OFF_EVENTS!$C$5:$C$104) -> 0 | H74: =D74-E74-F74+G74 -> -557.82341 | I74: =J73 -> -29047.639 | J74: =I74+H74 -> -29605.462
A75: =SETUP!$B$4+71 -> 46115 | B75: =TEXT(A75,"ddd") -> Fri | C75: =SETUP!$B$5*(1+SETUP!$B$17) -> 1500 | D75: =C75*(SETUP!$B$6+SETUP!$B$18) -> 345 | E75: =C75*(SETUP!$B$7+SETUP!$B$22) -> 525 | F75: =((SETUP!$B$8*(1+SETUP!$B$19)+SETUP!$B$9*(1+SETUP!$B$20)+SETUP!$B$10*(1+SETUP!$B$21))/SETUP!$B$14) -> 377.82341 | G75: =SUMIF(ONE_OFF_EVENTS!$A$5:$A$104,A75,ONE_OFF_EVENTS!$C$5:$C$104) -> 0 | H75: =D75-E75-F75+G75 -> -557.82341 | I75: =J74 -> -29605.462 | J75: =I75+H75 -> -30163.285
A76: =SETUP!$B$4+72 -> 46116 | B76: =TEXT(A76,"ddd") -> Sat | C76: =SETUP!$B$5*(1+SETUP!$B$17) -> 1500 | D76: =C76*(SETUP!$B$6+SETUP!$B$18) -> 345 | E76: =C76*(SETUP!$B$7+SETUP!$B$22) -> 525 | F76: =((SETUP!$B$8*(1+SETUP!$B$19)+SETUP!$B$9*(1+SETUP!$B$20)+SETUP!$B$10*(1+SETUP!$B$21))/SETUP!$B$14) -> 377.82341 | G76: =SUMIF(ONE_OFF_EVENTS!$A$5:$A$104,A76,ONE_OFF_EVENTS!$C$5:$C$104) -> 0 | H76: =D76-E76-F76+G76 -> -557.82341 | I76: =J75 -> -30163.285 | J76: =I76+H76 -> -30721.109
A77: =SETUP!$B$4+73 -> 46117 | B77: =TEXT(A77,"ddd") -> Sun | C77: =SETUP!$B$5*(1+SETUP!$B$17) -> 1500 | D77: =C77*(SETUP!$B$6+SETUP!$B$18) -> 345 | E77: =C77*(SETUP!$B$7+SETUP!$B$22) -> 525 | F77: =((SETUP!$B$8*(1+SETUP!$B$19)+SETUP!$B$9*(1+SETUP!$B$20)+SETUP!$B$10*(1+SETUP!$B$21))/SETUP!$B$14) -> 377.82341 | G77: =SUMIF(ONE_OFF_EVENTS!$A$5:$A$104,A77,ONE_OFF_EVENTS!$C$5:$C$104) -> 0 | H77: =D77-E77-F77+G77 -> -557.82341 | I77: =J76 -> -30721.109 | J77: =I77+H77 -> -31278.932
A78: =SETUP!$B$4+74 -> 46118 | B78: =TEXT(A78,"ddd") -> Mon | C78: =SETUP!$B$5*(1+SETUP!$B$17) -> 1500 | D78: =C78*(SETUP!$B$6+SETUP!$B$18) -> 345 | E78: =C78*(SETUP!$B$7+SETUP!$B$22) -> 525 | F78: =((SETUP!$B$8*(1+SETUP!$B$19)+SETUP!$B$9*(1+SETUP!$B$20)+SETUP!$B$10*(1+SETUP!$B$21))/SETUP!$B$14) -> 377.82341 | G78: =SUMIF(ONE_OFF_EVENTS!$A$5:$A$104,A78,ONE_OFF_EVENTS!$C$5:$C$104) -> 0 | H78: =D78-E78-F78+G78 -> -557.82341 | I78: =J77 -> -31278.932 | J78: =I78+H78 -> -31836.756
A79: =SETUP!$B$4+75 -> 46119 | B79: =TEXT(A79,"ddd") -> Tue | C79: =SETUP!$B$5*(1+SETUP!$B$17) -> 1500 | D79: =C79*(SETUP!$B$6+SETUP!$B$18) -> 345 | E79: =C79*(SETUP!$B$7+SETUP!$B$22) -> 525 | F79: =((SETUP!$B$8*(1+SETUP!$B$19)+SETUP!$B$9*(1+SETUP!$B$20)+SETUP!$B$10*(1+SETUP!$B$21))/SETUP!$B$14) -> 377.82341 | G79: =SUMIF(ONE_OFF_EVENTS!$A$5:$A$104,A79,ONE_OFF_EVENTS!$C$5:$C$104) -> 0 | H79: =D79-E79-F79+G79 -> -557.82341 | I79: =J78 -> -31836.756 | J79: =I79+H79 -> -32394.579
A80: =SETUP!$B$4+76 -> 46120 | B80: =TEXT(A80,"ddd") -> Wed | C80: =SETUP!$B$5*(1+SETUP!$B$17) -> 1500 | D80: =C80*(SETUP!$B$6+SETUP!$B$18) -> 345 | E80: =C80*(SETUP!$B$7+SETUP!$B$22) -> 525 | F80: =((SETUP!$B$8*(1+SETUP!$B$19)+SETUP!$B$9*(1+SETUP!$B$20)+SETUP!$B$10*(1+SETUP!$B$21))/SETUP!$B$14) -> 377.82341 | G80: =SUMIF(ONE_OFF_EVENTS!$A$5:$A$104,A80,ONE_OFF_EVENTS!$C$5:$C$104) -> 0 | H80: =D80-E80-F80+G80 -> -557.82341 | I80: =J79 -> -32394.579 | J80: =I80+H80 -> -32952.402
A81: =SETUP!$B$4+77 -> 46121 | B81: =TEXT(A81,"ddd") -> Thu | C81: =SETUP!$B$5*(1+SETUP!$B$17) -> 1500 | D81: =C81*(SETUP!$B$6+SETUP!$B$18) -> 345 | E81: =C81*(SETUP!$B$7+SETUP!$B$22) -> 525 | F81: =((SETUP!$B$8*(1+SETUP!$B$19)+SETUP!$B$9*(1+SETUP!$B$20)+SETUP!$B$10*(1+SETUP!$B$21))/SETUP!$B$14) -> 377.82341 | G81: =SUMIF(ONE_OFF_EVENTS!$A$5:$A$104,A81,ONE_OFF_EVENTS!$C$5:$C$104) -> 0 | H81: =D81-E81-F81+G81 -> -557.82341 | I81: =J80 -> -32952.402 | J81: =I81+H81 -> -33510.226
A82: =SETUP!$B$4+78 -> 46122 | B82: =TEXT(A82,"ddd") -> Fri | C82: =SETUP!$B$5*(1+SETUP!$B$17) -> 1500 | D82: =C82*(SETUP!$B$6+SETUP!$B$18) -> 345 | E82: =C82*(SETUP!$B$7+SETUP!$B$22) -> 525 | F82: =((SETUP!$B$8*(1+SETUP!$B$19)+SETUP!$B$9*(1+SETUP!$B$20)+SETUP!$B$10*(1+SETUP!$B$21))/SETUP!$B$14) -> 377.82341 | G82: =SUMIF(ONE_OFF_EVENTS!$A$5:$A$104,A82,ONE_OFF_EVENTS!$C$5:$C$104) -> 0 | H82: =D82-E82-F82+G82 -> -557.82341 | I82: =J81 -> -33510.226 | J82: =I82+H82 -> -34068.049
A83: =SETUP!$B$4+79 -> 46123 | B83: =TEXT(A83,"ddd") -> Sat | C83: =SETUP!$B$5*(1+SETUP!$B$17) -> 1500 | D83: =C83*(SETUP!$B$6+SETUP!$B$18) -> 345 | E83: =C83*(SETUP!$B$7+SETUP!$B$22) -> 525 | F83: =((SETUP!$B$8*(1+SETUP!$B$19)+SETUP!$B$9*(1+SETUP!$B$20)+SETUP!$B$10*(1+SETUP!$B$21))/SETUP!$B$14) -> 377.82341 | G83: =SUMIF(ONE_OFF_EVENTS!$A$5:$A$104,A83,ONE_OFF_EVENTS!$C$5:$C$104) -> 0 | H83: =D83-E83-F83+G83 -> -557.82341 | I83: =J82 -> -34068.049 | J83: =I83+H83 -> -34625.873
A84: =SETUP!$B$4+80 -> 46124 | B84: =TEXT(A84,"ddd") -> Sun | C84: =SETUP!$B$5*(1+SETUP!$B$17) -> 1500 | D84: =C84*(SETUP!$B$6+SETUP!$B$18) -> 345 | E84: =C84*(SETUP!$B$7+SETUP!$B$22) -> 525 | F84: =((SETUP!$B$8*(1+SETUP!$B$19)+SETUP!$B$9*(1+SETUP!$B$20)+SETUP!$B$10*(1+SETUP!$B$21))/SETUP!$B$14) -> 377.82341 | G84: =SUMIF(ONE_OFF_EVENTS!$A$5:$A$104,A84,ONE_OFF_EVENTS!$C$5:$C$104) -> 0 | H84: =D84-E84-F84+G84 -> -557.82341 | I84: =J83 -> -34625.873 | J84: =I84+H84 -> -35183.696
A85: =SETUP!$B$4+81 -> 46125 | B85: =TEXT(A85,"ddd") -> Mon | C85: =SETUP!$B$5*(1+SETUP!$B$17) -> 1500 | D85: =C85*(SETUP!$B$6+SETUP!$B$18) -> 345 | E85: =C85*(SETUP!$B$7+SETUP!$B$22) -> 525 | F85: =((SETUP!$B$8*(1+SETUP!$B$19)+SETUP!$B$9*(1+SETUP!$B$20)+SETUP!$B$10*(1+SETUP!$B$21))/SETUP!$B$14) -> 377.82341 | G85: =SUMIF(ONE_OFF_EVENTS!$A$5:$A$104,A85,ONE_OFF_EVENTS!$C$5:$C$104) -> 0 | H85: =D85-E85-F85+G85 -> -557.82341 | I85: =J84 -> -35183.696 | J85: =I85+H85 -> -35741.52
A86: =SETUP!$B$4+82 -> 46126 | B86: =TEXT(A86,"ddd") -> Tue | C86: =SETUP!$B$5*(1+SETUP!$B$17) -> 1500 | D86: =C86*(SETUP!$B$6+SETUP!$B$18) -> 345 | E86: =C86*(SETUP!$B$7+SETUP!$B$22) -> 525 | F86: =((SETUP!$B$8*(1+SETUP!$B$19)+SETUP!$B$9*(1+SETUP!$B$20)+SETUP!$B$10*(1+SETUP!$B$21))/SETUP!$B$14) -> 377.82341 | G86: =SUMIF(ONE_OFF_EVENTS!$A$5:$A$104,A86,ONE_OFF_EVENTS!$C$5:$C$104) -> 0 | H86: =D86-E86-F86+G86 -> -557.82341 | I86: =J85 -> -35741.52 | J86: =I86+H86 -> -36299.343
A87: =SETUP!$B$4+83 -> 46127 | B87: =TEXT(A87,"ddd") -> Wed | C87: =SETUP!$B$5*(1+SETUP!$B$17) -> 1500 | D87: =C87*(SETUP!$B$6+SETUP!$B$18) -> 345 | E87: =C87*(SETUP!$B$7+SETUP!$B$22) -> 525 | F87: =((SETUP!$B$8*(1+SETUP!$B$19)+SETUP!$B$9*(1+SETUP!$B$20)+SETUP!$B$10*(1+SETUP!$B$21))/SETUP!$B$14) -> 377.82341 | G87: =SUMIF(ONE_OFF_EVENTS!$A$5:$A$104,A87,ONE_OFF_EVENTS!$C$5:$C$104) -> 0 | H87: =D87-E87-F87+G87 -> -557.82341 | I87: =J86 -> -36299.343 | J87: =I87+H87 -> -36857.166
A88: =SETUP!$B$4+84 -> 46128 | B88: =TEXT(A88,"ddd") -> Thu | C88: =SETUP!$B$5*(1+SETUP!$B$17) -> 1500 | D88: =C88*(SETUP!$B$6+SETUP!$B$18) -> 345 | E88: =C88*(SETUP!$B$7+SETUP!$B$22) -> 525 | F88: =((SETUP!$B$8*(1+SETUP!$B$19)+SETUP!$B$9*(1+SETUP!$B$20)+SETUP!$B$10*(1+SETUP!$B$21))/SETUP!$B$14) -> 377.82341 | G88: =SUMIF(ONE_OFF_EVENTS!$A$5:$A$104,A88,ONE_OFF_EVENTS!$C$5:$C$104) -> 0 | H88: =D88-E88-F88+G88 -> -557.82341 | I88: =J87 -> -36857.166 | J88: =I88+H88 -> -37414.99
A89: =SETUP!$B$4+85 -> 46129 | B89: =TEXT(A89,"ddd") -> Fri | C89: =SETUP!$B$5*(1+SETUP!$B$17) -> 1500 | D89: =C89*(SETUP!$B$6+SETUP!$B$18) -> 345 | E89: =C89*(SETUP!$B$7+SETUP!$B$22) -> 525 | F89: =((SETUP!$B$8*(1+SETUP!$B$19)+SETUP!$B$9*(1+SETUP!$B$20)+SETUP!$B$10*(1+SETUP!$B$21))/SETUP!$B$14) -> 377.82341 | G89: =SUMIF(ONE_OFF_EVENTS!$A$5:$A$104,A89,ONE_OFF_EVENTS!$C$5:$C$104) -> 0 | H89: =D89-E89-F89+G89 -> -557.82341 | I89: =J88 -> -37414.99 | J89: =I89+H89 -> -37972.813
A90: =SETUP!$B$4+86 -> 46130 | B90: =TEXT(A90,"ddd") -> Sat | C90: =SETUP!$B$5*(1+SETUP!$B$17) -> 1500 | D90: =C90*(SETUP!$B$6+SETUP!$B$18) -> 345 | E90: =C90*(SETUP!$B$7+SETUP!$B$22) -> 525 | F90: =((SETUP!$B$8*(1+SETUP!$B$19)+SETUP!$B$9*(1+SETUP!$B$20)+SETUP!$B$10*(1+SETUP!$B$21))/SETUP!$B$14) -> 377.82341 | G90: =SUMIF(ONE_OFF_EVENTS!$A$5:$A$104,A90,ONE_OFF_EVENTS!$C$5:$C$104) -> 0 | H90: =D90-E90-F90+G90 -> -557.82341 | I90: =J89 -> -37972.813 | J90: =I90+H90 -> -38530.637
A91: =SETUP!$B$4+87 -> 46131 | B91: =TEXT(A91,"ddd") -> Sun | C91: =SETUP!$B$5*(1+SETUP!$B$17) -> 1500 | D91: =C91*(SETUP!$B$6+SETUP!$B$18) -> 345 | E91: =C91*(SETUP!$B$7+SETUP!$B$22) -> 525 | F91: =((SETUP!$B$8*(1+SETUP!$B$19)+SETUP!$B$9*(1+SETUP!$B$20)+SETUP!$B$10*(1+SETUP!$B$21))/SETUP!$B$14) -> 377.82341 | G91: =SUMIF(ONE_OFF_EVENTS!$A$5:$A$104,A91,ONE_OFF_EVENTS!$C$5:$C$104) -> 0 | H91: =D91-E91-F91+G91 -> -557.82341 | I91: =J90 -> -38530.637 | J91: =I91+H91 -> -39088.46
A92: =SETUP!$B$4+88 -> 46132 | B92: =TEXT(A92,"ddd") -> Mon | C92: =SETUP!$B$5*(1+SETUP!$B$17) -> 1500 | D92: =C92*(SETUP!$B$6+SETUP!$B$18) -> 345 | E92: =C92*(SETUP!$B$7+SETUP!$B$22) -> 525 | F92: =((SETUP!$B$8*(1+SETUP!$B$19)+SETUP!$B$9*(1+SETUP!$B$20)+SETUP!$B$10*(1+SETUP!$B$21))/SETUP!$B$14) -> 377.82341 | G92: =SUMIF(ONE_OFF_EVENTS!$A$5:$A$104,A92,ONE_OFF_EVENTS!$C$5:$C$104) -> 0 | H92: =D92-E92-F92+G92 -> -557.82341 | I92: =J91 -> -39088.46 | J92: =I92+H92 -> -39646.283
A93: =SETUP!$B$4+89 -> 46133 | B93: =TEXT(A93,"ddd") -> Tue | C93: =SETUP!$B$5*(1+SETUP!$B$17) -> 1500 | D93: =C93*(SETUP!$B$6+SETUP!$B$18) -> 345 | E93: =C93*(SETUP!$B$7+SETUP!$B$22) -> 525 | F93: =((SETUP!$B$8*(1+SETUP!$B$19)+SETUP!$B$9*(1+SETUP!$B$20)+SETUP!$B$10*(1+SETUP!$B$21))/SETUP!$B$14) -> 377.82341 | G93: =SUMIF(ONE_OFF_EVENTS!$A$5:$A$104,A93,ONE_OFF_EVENTS!$C$5:$C$104) -> 0 | H93: =D93-E93-F93+G93 -> -557.82341 | I93: =J92 -> -39646.283 | J93: =I93+H93 -> -40204.107

Sheet SUMMARY
A1: SUMMARY
A3: Lowest cash in next 90 days | B3: =MIN(DAILY_PLANNER!J4:J93) -> -40204.107
A4: Ending cash (day 90) | B4: =DAILY_PLANNER!J93 -> -40204.107
A5: First day cash goes below £0 (if any) | B5: =IFERROR(INDEX(DAILY_PLANNER!A4:A93,MATCH(TRUE,DAILY_PLANNER!J4:J93<0,0)),"No shortfall forecast") -> No shortfall forecast
A6: Average daily net cash change | B6: =AVERAGE(DAILY_PLANNER!H4:H93) -> -557.82341
A8: Advisory
A9: If a shortfall is forecast, action is recommended (pricing, margin, costs, or sales volume). Use ONE_OFF_EVENTS to plan known payments and income.
