Workbook

Sheet INSTRUCTIONS
A1: Margin Tracker (Basic)
A3: Purpose
A4: Track what margin you EXPECT versus what margin you ACTUALLY achieve.
A5: This helps you spot underpricing, discount damage, and margin drift over time.
A7: How to use
A8: 1) Complete the SETUP tab (yellow cells only).
A9: 2) Enter weekly or monthly figures in the MARGIN_TRACKER tab.
A10: 3) Review variance and flags.
A12: Notes
A13: • All figures are EX VAT.
A14: • Use estimates if exact figures are not available.
A15: • This is a monitoring tool, not an accounting system.

Sheet SETUP
A1: SETUP (fill yellow cells)
A3: Target margin % (what you expect to achieve) | B3: 0.45 | C3: Tip | D3: If unsure, use 40% margin and 1.5–2% card fees.
A4: Card fees % (average) | B4: 0.018 | C4: Tip | D4: If unsure, use 40% margin and 1.5–2% card fees.

Sheet MARGIN_TRACKER
A3: Period (Week / Month) | B3: Total Sales (ex VAT) | C3: Cost of Stock (ex VAT) | D3: Gross Margin % | E3: Margin after Card Fees % | F3: Target Margin % | G3: Variance vs Target % | H3: Status
D4: =IF(B4>0,(B4-C4)/B4,"") | E4: =IF(D4="","",D4-SETUP!$B$4) | F4: =SETUP!$B$3 -> 0.45 | G4: =IF(E4="","",E4-F4) | H4: =IF(G4="","",IF(G4<0,"BELOW TARGET","ON / ABOVE TARGET"))
D5: =IF(B5>0,(B5-C5)/B5,"") | E5: =IF(D5="","",D5-SETUP!$B$4) | F5: =SETUP!$B$3 -> 0.45 | G5: =IF(E5="","",E5-F5) | H5: =IF(G5="","",IF(G5<0,"BELOW TARGET","ON / ABOVE TARGET"))
D6: =IF(B6>0,(B6-C6)/B6,"") | E6: =IF(D6="","",D6-SETUP!$B$4) | F6: =SETUP!$B$3 -> 0.45 | G6: =IF(E6="","",E6-F6) | H6: =IF(G6="","",IF(G6<0,"BELOW TARGET","ON / ABOVE TARGET"))
D7: =IF(B7>0,(B7-C7)/B7,"") | E7: =IF(D7="","",D7-SETUP!$B$4) | F7: =SETUP!$B$3 -> 0.45 | G7: =IF(E7="","",E7-F7) | H7: =IF(G7="","",IF(G7<0,"BELOW TARGET","ON / ABOVE TARGET"))
D8: =IF(B8>0,(B8-C8)/B8,"") | E8: =IF(D8="","",D8-SETUP!$B$4) | F8: =SETUP!$B$3 -> 0.45 | G8: =IF(E8="","",E8-F8) | H8: =IF(G8="","",IF(G8<0,"BELOW TARGET","ON / ABOVE TARGET"))
D9: =IF(B9>0,(B9-C9)/B9,"") | E9: =IF(D9="","",D9-SETUP!$B$4) | F9: =SETUP!$B$3 -> 0.45 | G9: =IF(E9="","",E9-F9) | H9: =IF(G9="","",IF(G9<0,"BELOW TARGET","ON / ABOVE TARGET"))
D10: =IF(B10>0,(B10-C10)/B10,"") | E10: =IF(D10="","",D10-SETUP!$B$4) | F10: =SETUP!$B$3 -> 0.45 | G10: =IF(E10="","",E10-F10) | H10: =IF(G10="","",IF(G10<0,"BELOW TARGET","ON / ABOVE TARGET"))
D11: =IF(B11>0,(B11-C11)/B11,"") | E11: =IF(D11="","",D11-SETUP!$B$4) | F11: =SETUP!$B$3 -> 0.45 | G11: =IF(E11="","",E11-F11) | H11: =IF(G11="","",IF(G11<0,"BELOW TARGET","ON / ABOVE TARGET"))
D12: =IF(B12>0,(B12-C12)/B12,"") | E12: =IF(D12="","",D12-SETUP!$B$4) | F12: =SETUP!$B$3 -> 0.45 | G12: =IF(E12="","",E12-F12) | H12: =IF(G12="","",IF(G12<0,"BELOW TARGET","ON / ABOVE TARGET"))
D13: =IF(B13>0,(B13-C13)/B13,"") | E13: =IF(D13="","",D13-SETUP!$B$4) | F13: =SETUP!$B$3 -> 0.45 | G13: =IF(E13="","",E13-F13) | H13: =IF(G13="","",IF(G13<0,"BELOW TARGET","ON / ABOVE TARGET"))
D14: =IF(B14>0,(B14-C14)/B14,"") | E14: =IF(D14="","",D14-SETUP!$B$4) | F14: =SETUP!$B$3 -> 0.45 | G14: =IF(E14="","",E14-F14) | H14: =IF(G14="","",IF(G14<0,"BELOW TARGET","ON / ABOVE TARGET"))
D15: =IF(B15>0,(B15-C15)/B15,"") | E15: =IF(D15="","",D15-SETUP!$B$4) | F15: =SETUP!$B$3 -> 0.45 | G15: =IF(E15="","",E15-F15) | H15: =IF(G15="","",IF(G15<0,"BELOW TARGET","ON / ABOVE TARGET"))
... D204: =IF(B204>0,(B204-C204)/B204,"") | E204: =IF(D204="","",D204-SETUP!$B$4) | F204: =SETUP!$B$3 -> 0.45 | G204: =IF(E204="","",E204-F204) | H204: =IF(G204="","",IF(G204<0,"BELOW TARGET","ON / ABOVE TARGET"))
