Workbook

Sheet INSTRUCTIONS
A1: Pricing Calculator (Basic)
A3: What this does
A4: Enter your product costs and the margin you want. The sheet shows minimum, target and growth prices.
A6: Key points
A7: • Enter costs and prices EX VAT.
A8: • If you are VAT registered, the sheet also shows the INC VAT selling price.
A9: • Card fees are included in the 'target' price so your margin is not quietly eaten by fees.
A11: How to use
A12: 1) Go to SETUP and fill in the yellow cells (your VAT and fee settings).
A13: 2) Go to CALCULATOR and enter your products in the yellow columns.
A14: 3) Read the price recommendations (Minimum / Target / Growth).
A16: Definitions
... A19: Growth Price: Target Price plus a small extra margin for growth (optional).

Sheet SETUP
A1: SETUP (fill yellow cells)
A3: VAT registered? (Yes/No) | B3: No | C3: Tip | D3: Type Yes if you add VAT to your prices. Type No if you do not charge VAT.
A4: VAT rate (e.g. 20%) | B4: 0.2 | C4: Tip | D4: UK standard VAT is 20%. Leave as 20% unless you know yours is different.
A5: Card fees % (e.g. 1.8%) | B5: 0.018 | C5: Tip | D5: If unsure, use 1.5%–2.0%.
A6: Target margin % (e.g. 45%) | B6: 0.45 | C6: Tip | D6: If unsure, start with 40% and adjust.
A7: Extra margin for growth (optional, e.g. 10%) | B7: 0.1 | C7: Tip | D7: Leave as 10% if unsure. Set to 0% if you do not want a growth price.

Sheet CALCULATOR
A1: CALCULATOR (enter yellow cells)
A3: Item / Product | B3: Cost (ex VAT) | C3: Current Price (ex VAT) (optional) | D3: Minimum Price (ex VAT) | E3: Target Price (ex VAT) | F3: Growth Price (ex VAT) | G3: Target Price (inc VAT) | H3: Growth Price (inc VAT) | I3: Actual Margin % (if current price given) | J3: Profit per sale at Target (ex VAT) | K3: Underpriced vs Target?
D4: =IF($B4>0,$B4/(1-SETUP!$B$5),"") | E4: =IF($B4>0,IF((1-(SETUP!$B$6+SETUP!$B$5))<=0,"Check setup",$B4/(1-(SETUP!$B$6+SETUP!$B$5))),"") | F4: =IF($B4>0,IF((1-(SETUP!$B$6+SETUP!$B$5+SETUP!$B$7))<=0,"Check setup",IF(SETUP!$B$7=0,$E4,$B4/(1-(SETUP!$B$6+SETUP!$B$5+SETUP!$B$7)))),"") | G4: =IF(LOWER(SETUP!$B$3)="yes",IF($E4="","",$E4*(1+SETUP!$B$4)),"") | H4: =IF(LOWER(SETUP!$B$3)="yes",IF($F4="","",$F4*(1+SETUP!$B$4)),"") | I4: =IF($C4>0,($C4-$B4-($C4*SETUP!$B$5))/$C4,"") | J4: =IF($E4>0,$E4-$B4-($E4*SETUP!$B$5),"") -> #VALUE! | K4: =IF($C4>0,IF($C4<$E4,"YES","NO"),"")
D5: =IF($B5>0,$B5/(1-SETUP!$B$5),"") | E5: =IF($B5>0,IF((1-(SETUP!$B$6+SETUP!$B$5))<=0,"Check setup",$B5/(1-(SETUP!$B$6+SETUP!$B$5))),"") | F5: =IF($B5>0,IF((1-(SETUP!$B$6+SETUP!$B$5+SETUP!$B$7))<=0,"Check setup",IF(SETUP!$B$7=0,$E5,$B5/(1-(SETUP!$B$6+SETUP!$B$5+SETUP!$B$7)))),"") | G5: =IF(LOWER(SETUP!$B$3)="yes",IF($E5="","",$E5*(1+SETUP!$B$4)),"") | H5: =IF(LOWER(SETUP!$B$3)="yes",IF($F5="","",$F5*(1+SETUP!$B$4)),"") | I5: =IF($C5>0,($C5-$B5-($C5*SETUP!$B$5))/$C5,"") | J5: =IF($E5>0,$E5-$B5-($E5*SETUP!$B$5),"") -> #VALUE! | K5: =IF($C5>0,IF($C5<$E5,"YES","NO"),"")
D6: =IF($B6>0,$B6/(1-SETUP!$B$5),"") | E6: =IF($B6>0,IF((1-(SETUP!$B$6+SETUP!$B$5))<=0,"Check setup",$B6/(1-(SETUP!$B$6+SETUP!$B$5))),"") | F6: =IF($B6>0,IF((1-(SETUP!$B$6+SETUP!$B$5+SETUP!$B$7))<=0,"Check setup",IF(SETUP!$B$7=0,$E6,$B6/(1-(SETUP!$B$6+SETUP!$B$5+SETUP!$B$7)))),"") | G6: =IF(LOWER(SETUP!$B$3)="yes",IF($E6="","",$E6*(1+SETUP!$B$4)),"") | H6: =IF(LOWER(SETUP!$B$3)="yes",IF($F6="","",$F6*(1+SETUP!$B$4)),"") | I6: =IF($C6>0,($C6-$B6-($C6*SETUP!$B$5))/$C6,"") | J6: =IF($E6>0,$E6-$B6-($E6*SETUP!$B$5),"") -> #VALUE! | K6: =IF($C6>0,IF($C6<$E6,"YES","NO"),"")
D7: =IF($B7>0,$B7/(1-SETUP!$B$5),"") | E7: =IF($B7>0,IF((1-(SETUP!$B$6+SETUP!$B$5))<=0,"Check setup",$B7/(1-(SETUP!$B$6+SETUP!$B$5))),"") | F7: =IF($B7>0,IF((1-(SETUP!$B$6+SETUP!$B$5+SETUP!$B$7))<=0,"Check setup",IF(SETUP!$B$7=0,$E7,$B7/(1-(SETUP!$B$6+SETUP!$B$5+SETUP!$B$7)))),"") | G7: =IF(LOWER(SETUP!$B$3)="yes",IF($E7="","",$E7*(1+SETUP!$B$4)),"") | H7: =IF(LOWER(SETUP!$B$3)="yes",IF($F7="","",$F7*(1+SETUP!$B$4)),"") | I7: =IF($C7>0,($C7-$B7-($C7*SETUP!$B$5))/$C7,"") | J7: =IF($E7>0,$E7-$B7-($E7*SETUP!$B$5),"") -> #VALUE! | K7: =IF($C7>0,IF($C7<$E7,"YES","NO"),"")
D8: =IF($B8>0,$B8/(1-SETUP!$B$5),"") | E8: =IF($B8>0,IF((1-(SETUP!$B$6+SETUP!$B$5))<=0,"Check setup",$B8/(1-(SETUP!$B$6+SETUP!$B$5))),"") | F8: =IF($B8>0,IF((1-(SETUP!$B$6+SETUP!$B$5+SETUP!$B$7))<=0,"Check setup",IF(SETUP!$B$7=0,$E8,$B8/(1-(SETUP!$B$6+SETUP!$B$5+SETUP!$B$7)))),"") | G8: =IF(LOWER(SETUP!$B$3)="yes",IF($E8="","",$E8*(1+SETUP!$B$4)),"") | H8: =IF(LOWER(SETUP!$B$3)="yes",IF($F8="","",$F8*(1+SETUP!$B$4)),"") | I8: =IF($C8>0,($C8-$B8-($C8*SETUP!$B$5))/$C8,"") | J8: =IF($E8>0,$E8-$B8-($E8*SETUP!$B$5),"") -> #VALUE! | K8: =IF($C8>0,IF($C8<$E8,"YES","NO"),"")
D9: =IF($B9>0,$B9/(1-SETUP!$B$5),"") | E9: =IF($B9>0,IF((1-(SETUP!$B$6+SETUP!$B$5))<=0,"Check setup",$B9/(1-(SETUP!$B$6+SETUP!$B$5))),"") | F9: =IF($B9>0,IF((1-(SETUP!$B$6+SETUP!$B$5+SETUP!$B$7))<=0,"Check setup",IF(SETUP!$B$7=0,$E9,$B9/(1-(SETUP!$B$6+SETUP!$B$5+SETUP!$B$7)))),"") | G9: =IF(LOWER(SETUP!$B$3)="yes",IF($E9="","",$E9*(1+SETUP!$B$4)),"") | H9: =IF(LOWER(SETUP!$B$3)="yes",IF($F9="","",$F9*(1+SETUP!$B$4)),"") | I9: =IF($C9>0,($C9-$B9-($C9*SETUP!$B$5))/$C9,"") | J9: =IF($E9>0,$E9-$B9-($E9*SETUP!$B$5),"") -> #VALUE! | K9: =IF($C9>0,IF($C9<$E9,"YES","NO"),"")
D10: =IF($B10>0,$B10/(1-SETUP!$B$5),"") | E10: =IF($B10>0,IF((1-(SETUP!$B$6+SETUP!$B$5))<=0,"Check setup",$B10/(1-(SETUP!$B$6+SETUP!$B$5))),"") | F10: =IF($B10>0,IF((1-(SETUP!$B$6+SETUP!$B$5+SETUP!$B$7))<=0,"Check setup",IF(SETUP!$B$7=0,$E10,$B10/(1-(SETUP!$B$6+SETUP!$B$5+SETUP!$B$7)))),"") | G10: =IF(LOWER(SETUP!$B$3)="yes",IF($E10="","",$E10*(1+SETUP!$B$4)),"") | H10: =IF(LOWER(SETUP!$B$3)="yes",IF($F10="","",$F10*(1+SETUP!$B$4)),"") | I10: =IF($C10>0,($C10-$B10-($C10*SETUP!$B$5))/$C10,"") | J10: =IF($E10>0,$E10-$B10-($E10*SETUP!$B$5),"") -> #VALUE! | K10: =IF($C10>0,IF($C10<$E10,"YES","NO"),"")
D11: =IF($B11>0,$B11/(1-SETUP!$B$5),"") | E11: =IF($B11>0,IF((1-(SETUP!$B$6+SETUP!$B$5))<=0,"Check setup",$B11/(1-(SETUP!$B$6+SETUP!$B$5))),"") | F11: =IF($B11>0,IF((1-(SETUP!$B$6+SETUP!$B$5+SETUP!$B$7))<=0,"Check setup",IF(SETUP!$B$7=0,$E11,$B11/(1-(SETUP!$B$6+SETUP!$B$5+SETUP!$B$7)))),"") | G11: =IF(LOWER(SETUP!$B$3)="yes",IF($E11="","",$E11*(1+SETUP!$B$4)),"") | H11: =IF(LOWER(SETUP!$B$3)="yes",IF($F11="","",$F11*(1+SETUP!$B$4)),"") | I11: =IF($C11>0,($C11-$B11-($C11*SETUP!$B$5))/$C11,"") | J11: =IF($E11>0,$E11-$B11-($E11*SETUP!$B$5),"") -> #VALUE! | K11: =IF($C11>0,IF($C11<$E11,"YES","NO"),"")
D12: =IF($B12>0,$B12/(1-SETUP!$B$5),"") | E12: =IF($B12>0,IF((1-(SETUP!$B$6+SETUP!$B$5))<=0,"Check setup",$B12/(1-(SETUP!$B$6+SETUP!$B$5))),"") | F12: =IF($B12>0,IF((1-(SETUP!$B$6+SETUP!$B$5+SETUP!$B$7))<=0,"Check setup",IF(SETUP!$B$7=0,$E12,$B12/(1-(SETUP!$B$6+SETUP!$B$5+SETUP!$B$7)))),"") | G12: =IF(LOWER(SETUP!$B$3)="yes",IF($E12="","",$E12*(1+SETUP!$B$4)),"") | H12: =IF(LOWER(SETUP!$B$3)="yes",IF($F12="","",$F12*(1+SETUP!$B$4)),"") | I12: =IF($C12>0,($C12-$B12-($C12*SETUP!$B$5))/$C12,"") | J12: =IF($E12>0,$E12-$B12-($E12*SETUP!$B$5),"") -> #VALUE! | K12: =IF($C12>0,IF($C12<$E12,"YES","NO"),"")
D13: =IF($B13>0,$B13/(1-SETUP!$B$5),"") | E13: =IF($B13>0,IF((1-(SETUP!$B$6+SETUP!$B$5))<=0,"Check setup",$B13/(1-(SETUP!$B$6+SETUP!$B$5))),"") | F13: =IF($B13>0,IF((1-(SETUP!$B$6+SETUP!$B$5+SETUP!$B$7))<=0,"Check setup",IF(SETUP!$B$7=0,$E13,$B13/(1-(SETUP!$B$6+SETUP!$B$5+SETUP!$B$7)))),"") | G13: =IF(LOWER(SETUP!$B$3)="yes",IF($E13="","",$E13*(1+SETUP!$B$4)),"") | H13: =IF(LOWER(SETUP!$B$3)="yes",IF($F13="","",$F13*(1+SETUP!$B$4)),"") | I13: =IF($C13>0,($C13-$B13-($C13*SETUP!$B$5))/$C13,"") | J13: =IF($E13>0,$E13-$B13-($E13*SETUP!$B$5),"") -> #VALUE! | K13: =IF($C13>0,IF($C13<$E13,"YES","NO"),"")
D14: =IF($B14>0,$B14/(1-SETUP!$B$5),"") | E14: =IF($B14>0,IF((1-(SETUP!$B$6+SETUP!$B$5))<=0,"Check setup",$B14/(1-(SETUP!$B$6+SETUP!$B$5))),"") | F14: =IF($B14>0,IF((1-(SETUP!$B$6+SETUP!$B$5+SETUP!$B$7))<=0,"Check setup",IF(SETUP!$B$7=0,$E14,$B14/(1-(SETUP!$B$6+SETUP!$B$5+SETUP!$B$7)))),"") | G14: =IF(LOWER(SETUP!$B$3)="yes",IF($E14="","",$E14*(1+SETUP!$B$4)),"") | H14: =IF(LOWER(SETUP!$B$3)="yes",IF($F14="","",$F14*(1+SETUP!$B$4)),"") | I14: =IF($C14>0,($C14-$B14-($C14*SETUP!$B$5))/$C14,"") | J14: =IF($E14>0,$E14-$B14-($E14*SETUP!$B$5),"") -> #VALUE! | K14: =IF($C14>0,IF($C14<$E14,"YES","NO"),"")
D15: =IF($B15>0,$B15/(1-SETUP!$B$5),"") | E15: =IF($B15>0,IF((1-(SETUP!$B$6+SETUP!$B$5))<=0,"Check setup",$B15/(1-(SETUP!$B$6+SETUP!$B$5))),"") | F15: =IF($B15>0,IF((1-(SETUP!$B$6+SETUP!$B$5+SETUP!$B$7))<=0,"Check setup",IF(SETUP!$B$7=0,$E15,$B15/(1-(SETUP!$B$6+SETUP!$B$5+SETUP!$B$7)))),"") | G15: =IF(LOWER(SETUP!$B$3)="yes",IF($E15="","",$E15*(1+SETUP!$B$4)),"") | H15: =IF(LOWER(SETUP!$B$3)="yes",IF($F15="","",$F15*(1+SETUP!$B$4)),"") | I15: =IF($C15>0,($C15-$B15-($C15*SETUP!$B$5))/$C15,"") | J15: =IF($E15>0,$E15-$B15-($E15*SETUP!$B$5),"") -> #VALUE! | K15: =IF($C15>0,IF($C15<$E15,"YES","NO"),"")
... D203: =IF($B203>0,$B203/(1-SETUP!$B$5),"") | E203: =IF($B203>0,IF((1-(SETUP!$B$6+SETUP!$B$5))<=0,"Check setup",$B203/(1-(SETUP!$B$6+SETUP!$B$5))),"") | F203: =IF($B203>0,IF((1-(SETUP!$B$6+SETUP!$B$5+SETUP!$B$7))<=0,"Check setup",IF(SETUP!$B$7=0,$E203,$B203/(1-(SETUP!$B$6+SETUP!$B$5+SETUP!$B$7)))),"") | G203: =IF(LOWER(SETUP!$B$3)="yes",IF($E203="","",$E203*(1+SETUP!$B$4)),"") | H203: =IF(LOWER(SETUP!$B$3)="yes",IF($F203="","",$F203*(1+SETUP!$B$4)),"") | I203: =IF($C203>0,($C203-$B203-($C203*SETUP!$B$5))/$C203,"") | J203: =IF($E203>0,$E203-$B203-($E203*SETUP!$B$5),"") -> #VALUE! | K203: =IF($C203>0,IF($C203<$E203,"YES","NO"),"")
